Workbook

Sheet Summary
A1: Opportunities — Test Cases
A3: Page | B3: https://qa-crm.asquareab.com/opportunities (and Leads › Ready to Convert for conversion)
A4: Build | B4: v1.0 1910-49
A5: Source | B5: Use cases UC-OPP-001 … UC-OPP-012 in Asquare_CRM_Opportunities_Use_Cases.xlsx; each use case's "Related Test Case IDs" (OPP-001 … OPP-059) written out here. OPP-060 is extra (UC-OPP-003 "record missing").
A6: Explored on | B6: 20/21-Oct-2026 (CRM Administrator, QA data)
A7: Scope | B7: Opportunities list, KPI cards, search, sort, paging, Board view and filters, Opportunity Detail, lead conversion, site visit / stage change, notes, Mark Lost, closed records, delete and access control
A8: How to use | B8: Fill "Status" (Not Started / Pass / Fail / Blocked / Not Applicable) and "Remarks" on the Test Cases sheet; the counts below update automatically.
A9: Automation | B9: Every test case is automated in tests/opportunities/ ("Automated in" column); test names, steps and expected results come from this sheet. Run: npm run test:opportunities. Tests on lifecycle.spec.ts change QA data: each run converts one Ready to Convert lead and marks the new opportunity Lost.
A10: Last run | B10: 22-Oct-2026 12:05, build v1.0 1910-49 — automated (tests/opportunities): 71 passed, 6 failed, 2 blocked (skipped by design); OPP-039 then passed on three reruns after a test-timing fix, so of the 78 test cases 71 pass, 5 fail, 2 blocked. Defect report: reports/CRM_Defect_Report_2026-10-22_1205.xlsx
A12: By use case | B12: Test cases | C12: High | D12: Pass | E12: Fail
A13: UC-OPP-001 View Opportunities | B13: =COUNTIF('Test Cases'!$B$2:$B$79,"*"&LEFT(A13,10)&"*") -> 16 | C13: =COUNTIFS('Test Cases'!$B$2:$B$79,"*"&LEFT(A13,10)&"*",'Test Cases'!$K$2:$K$79,"High") -> 10 | D13: =COUNTIFS('Test Cases'!$B$2:$B$79,"*"&LEFT(A13,10)&"*",'Test Cases'!$L$2:$L$79,"Pass") -> 15 | E13: =COUNTIFS('Test Cases'!$B$2:$B$79,"*"&LEFT(A13,10)&"*",'Test Cases'!$L$2:$L$79,"Fail") -> 1
A14: UC-OPP-002 Create Opportunity | B14: =COUNTIF('Test Cases'!$B$2:$B$79,"*"&LEFT(A14,10)&"*") -> 11 | C14: =COUNTIFS('Test Cases'!$B$2:$B$79,"*"&LEFT(A14,10)&"*",'Test Cases'!$K$2:$K$79,"High") -> 9 | D14: =COUNTIFS('Test Cases'!$B$2:$B$79,"*"&LEFT(A14,10)&"*",'Test Cases'!$L$2:$L$79,"Pass") -> 11 | E14: =COUNTIFS('Test Cases'!$B$2:$B$79,"*"&LEFT(A14,10)&"*",'Test Cases'!$L$2:$L$79,"Fail") -> 0
A15: UC-OPP-003 View Opportunity Details | B15: =COUNTIF('Test Cases'!$B$2:$B$79,"*"&LEFT(A15,10)&"*") -> 4 | C15: =COUNTIFS('Test Cases'!$B$2:$B$79,"*"&LEFT(A15,10)&"*",'Test Cases'!$K$2:$K$79,"High") -> 3 | D15: =COUNTIFS('Test Cases'!$B$2:$B$79,"*"&LEFT(A15,10)&"*",'Test Cases'!$L$2:$L$79,"Pass") -> 3 | E15: =COUNTIFS('Test Cases'!$B$2:$B$79,"*"&LEFT(A15,10)&"*",'Test Cases'!$L$2:$L$79,"Fail") -> 1
A16: UC-OPP-004 Edit Opportunity | B16: =COUNTIF('Test Cases'!$B$2:$B$79,"*"&LEFT(A16,10)&"*") -> 7 | C16: =COUNTIFS('Test Cases'!$B$2:$B$79,"*"&LEFT(A16,10)&"*",'Test Cases'!$K$2:$K$79,"High") -> 5 | D16: =COUNTIFS('Test Cases'!$B$2:$B$79,"*"&LEFT(A16,10)&"*",'Test Cases'!$L$2:$L$79,"Pass") -> 6 | E16: =COUNTIFS('Test Cases'!$B$2:$B$79,"*"&LEFT(A16,10)&"*",'Test Cases'!$L$2:$L$79,"Fail") -> 0
A17: UC-OPP-005 Search Opportunity | B17: =COUNTIF('Test Cases'!$B$2:$B$79,"*"&LEFT(A17,10)&"*") -> 6 | C17: =COUNTIFS('Test Cases'!$B$2:$B$79,"*"&LEFT(A17,10)&"*",'Test Cases'!$K$2:$K$79,"High") -> 3 | D17: =COUNTIFS('Test Cases'!$B$2:$B$79,"*"&LEFT(A17,10)&"*",'Test Cases'!$L$2:$L$79,"Pass") -> 6 | E17: =COUNTIFS('Test Cases'!$B$2:$B$79,"*"&LEFT(A17,10)&"*",'Test Cases'!$L$2:$L$79,"Fail") -> 0
A18: UC-OPP-006 Filter and Sort Opportunities | B18: =COUNTIF('Test Cases'!$B$2:$B$79,"*"&LEFT(A18,10)&"*") -> 7 | C18: =COUNTIFS('Test Cases'!$B$2:$B$79,"*"&LEFT(A18,10)&"*",'Test Cases'!$K$2:$K$79,"High") -> 0 | D18: =COUNTIFS('Test Cases'!$B$2:$B$79,"*"&LEFT(A18,10)&"*",'Test Cases'!$L$2:$L$79,"Pass") -> 6 | E18: =COUNTIFS('Test Cases'!$B$2:$B$79,"*"&LEFT(A18,10)&"*",'Test Cases'!$L$2:$L$79,"Fail") -> 1
A19: UC-OPP-007 Change Opportunity Stage | B19: =COUNTIF('Test Cases'!$B$2:$B$79,"*"&LEFT(A19,10)&"*") -> 7 | C19: =COUNTIFS('Test Cases'!$B$2:$B$79,"*"&LEFT(A19,10)&"*",'Test Cases'!$K$2:$K$79,"High") -> 4 | D19: =COUNTIFS('Test Cases'!$B$2:$B$79,"*"&LEFT(A19,10)&"*",'Test Cases'!$L$2:$L$79,"Pass") -> 5 | E19: =COUNTIFS('Test Cases'!$B$2:$B$79,"*"&LEFT(A19,10)&"*",'Test Cases'!$L$2:$L$79,"Fail") -> 2
A20: UC-OPP-008 Mark Opportunity as Won | B20: =COUNTIF('Test Cases'!$B$2:$B$79,"*"&LEFT(A20,10)&"*") -> 2 | C20: =COUNTIFS('Test Cases'!$B$2:$B$79,"*"&LEFT(A20,10)&"*",'Test Cases'!$K$2:$K$79,"High") -> 2 | D20: =COUNTIFS('Test Cases'!$B$2:$B$79,"*"&LEFT(A20,10)&"*",'Test Cases'!$L$2:$L$79,"Pass") -> 2 | E20: =COUNTIFS('Test Cases'!$B$2:$B$79,"*"&LEFT(A20,10)&"*",'Test Cases'!$L$2:$L$79,"Fail") -> 0
A21: UC-OPP-009 Mark Opportunity as Lost | B21: =COUNTIF('Test Cases'!$B$2:$B$79,"*"&LEFT(A21,10)&"*") -> 6 | C21: =COUNTIFS('Test Cases'!$B$2:$B$79,"*"&LEFT(A21,10)&"*",'Test Cases'!$K$2:$K$79,"High") -> 4 | D21: =COUNTIFS('Test Cases'!$B$2:$B$79,"*"&LEFT(A21,10)&"*",'Test Cases'!$L$2:$L$79,"Pass") -> 6 | E21: =COUNTIFS('Test Cases'!$B$2:$B$79,"*"&LEFT(A21,10)&"*",'Test Cases'!$L$2:$L$79,"Fail") -> 0
A22: UC-OPP-010 Convert Lead to Opportunity | B22: =COUNTIF('Test Cases'!$B$2:$B$79,"*"&LEFT(A22,10)&"*") -> 8 | C22: =COUNTIFS('Test Cases'!$B$2:$B$79,"*"&LEFT(A22,10)&"*",'Test Cases'!$K$2:$K$79,"High") -> 7 | D22: =COUNTIFS('Test Cases'!$B$2:$B$79,"*"&LEFT(A22,10)&"*",'Test Cases'!$L$2:$L$79,"Pass") -> 8 | E22: =COUNTIFS('Test Cases'!$B$2:$B$79,"*"&LEFT(A22,10)&"*",'Test Cases'!$L$2:$L$79,"Fail") -> 0
A23: UC-OPP-011 Delete Opportunity | B23: =COUNTIF('Test Cases'!$B$2:$B$79,"*"&LEFT(A23,10)&"*") -> 4 | C23: =COUNTIFS('Test Cases'!$B$2:$B$79,"*"&LEFT(A23,10)&"*",'Test Cases'!$K$2:$K$79,"High") -> 2 | D23: =COUNTIFS('Test Cases'!$B$2:$B$79,"*"&LEFT(A23,10)&"*",'Test Cases'!$L$2:$L$79,"Pass") -> 4 | E23: =COUNTIFS('Test Cases'!$B$2:$B$79,"*"&LEFT(A23,10)&"*",'Test Cases'!$L$2:$L$79,"Fail") -> 0
A24: UC-OPP-012 Validate Role-Based Access | B24: =COUNTIF('Test Cases'!$B$2:$B$79,"*"&LEFT(A24,10)&"*") -> 4 | C24: =COUNTIFS('Test Cases'!$B$2:$B$79,"*"&LEFT(A24,10)&"*",'Test Cases'!$K$2:$K$79,"High") -> 4 | D24: =COUNTIFS('Test Cases'!$B$2:$B$79,"*"&LEFT(A24,10)&"*",'Test Cases'!$L$2:$L$79,"Pass") -> 3 | E24: =COUNTIFS('Test Cases'!$B$2:$B$79,"*"&LEFT(A24,10)&"*",'Test Cases'!$L$2:$L$79,"Fail") -> 0
A25: Test cases (each counted once) | B25: =COUNTA('Test Cases'!$A$2:$A$79) -> 78 | C25: A test case linked to two use cases is counted under both above.
A27: By type | B27: Test cases
A28: Navigation | B28: =COUNTIF('Test Cases'!$J$2:$J$79,A28) -> 4
A29: UI | B29: =COUNTIF('Test Cases'!$J$2:$J$79,A29) -> 7
A30: Functional | B30: =COUNTIF('Test Cases'!$J$2:$J$79,A30) -> 35
A31: Negative | B31: =COUNTIF('Test Cases'!$J$2:$J$79,A31) -> 13
A32: Data | B32: =COUNTIF('Test Cases'!$J$2:$J$79,A32) -> 12
A33: Security | B33: =COUNTIF('Test Cases'!$J$2:$J$79,A33) -> 7
A35: By priority | B35: Test cases
A36: High | B36: =COUNTIF('Test Cases'!$K$2:$K$79,A36) -> 49
A37: Medium | B37: =COUNTIF('Test Cases'!$K$2:$K$79,A37) -> 29
A38: Low | B38: =COUNTIF('Test Cases'!$K$2:$K$79,A38) -> 0
A40: Execution status | B40: Test cases
A41: Not Started | B41: =COUNTIF('Test Cases'!$L$2:$L$79,A41) -> 0
A42: Pass | B42: =COUNTIF('Test Cases'!$L$2:$L$79,A42) -> 71
A43: Fail | B43: =COUNTIF('Test Cases'!$L$2:$L$79,A43) -> 5
A44: Blocked | B44: =COUNTIF('Test Cases'!$L$2:$L$79,A44) -> 2
A45: Not Applicable | B45: =COUNTIF('Test Cases'!$L$2:$L$79,A45) -> 0
A47: Observations | B47: =COUNTA(Observations!$A$2:$A$11) -> 10

Sheet Test Cases
A1: TC ID | B1: Use Case ID | C1: Use Case | D1: Test Case | E1: Preconditions | F1: Test Steps | G1: Test Data | H1: Expected Result | I1: Observed (21-Oct-2026 automated run, build v1.0 1910-49) | J1: Type | K1: Priority | L1: Status | M1: Remarks | N1: Automated in
A2: OPP-001 | B2: UC-OPP-001 | C2: View Opportunities | D2: Opportunities opens from the side menu | E2: Logged in as CRM Administrator | F2: 1. Open Home / Dashboard (/) 2. Click "Opportunities" in the main menu | H2: URL is /opportunities; heading "Opportunities"; the Opportunities menu item is highlighted | I2: As expected | J2: Navigation | K2: High | L2: Pass | N2: tests/opportunities/view.spec.ts
A3: OPP-002 | B3: UC-OPP-001 | C3: View Opportunities | D3: List loads without errors and shows every column | E3: Logged in as CRM Administrator | F3: 1. Open /opportunities 2. Look at the Pipeline list (List view) 3. Check the browser console and network log | H3: Columns Opportunity, Customer, Stage, Probability, Budget, Project, Created Date; every row shows an OPP-… number with its LD-… lead number, a customer and a probability in %; no JavaScript errors, failed API calls, NaN or undefined | I3: As expected | J3: UI | K3: High | L3: Pass | N3: tests/opportunities/view.spec.ts
A4: OPP-003 | B4: UC-OPP-001 | C4: View Opportunities | D4: KPI cards show loaded values | E4: Logged in as CRM Administrator | F4: 1. Open /opportunities 2. Read the Total, Open, Pipeline Value and Avg Probability cards and the "All amounts in" label | H4: All four cards show a value (not blank or —); Pipeline Value is in the base currency named in "All amounts in"; Avg Probability ends in % | I4: As expected | J4: UI | K4: Medium | L4: Pass | N4: tests/opportunities/view.spec.ts
A5: OPP-004 | B5: UC-OPP-001 | C5: View Opportunities | D5: Total = Open + Won + Lost | E5: Logged in as CRM Administrator | F5: 1. Open /opportunities; note Total and Open 2. Hover the "Formula" line of each card and note the counts in its tooltip 3. Switch to Board, choose "Won / Lost: all time" and note the Won and Lost column counts | H5: Total = Open + Won + Lost, and every count quoted in the KPI tooltips equals the card values | I5: Cards add up (47 + 79 + 9 = 135), but the tooltips are stale: "Open (43) + Won (78) + Lost (4)" = 125, and Pipeline Value / Avg Probability say "43 Open opportunities" while Open shows 47 | J5: Data | K5: High | L5: Fail | N5: tests/opportunities/view.spec.ts
A6: OPP-005 | B6: UC-OPP-001 | C6: View Opportunities | D6: Open, Pipeline Value and Avg Probability agree with the Board | E6: Logged in as CRM Administrator | F6: 1. Open /opportunities; note Open, Pipeline Value and Avg Probability 2. Switch to Board 3. Read "Open pipeline: N deals · amount" and the counts of Qualified, Site Visit, Negotiation, Reservation Ready and Proposal 4. Average the probability tag of every open card | H6: Open = Board open-pipeline deals = sum of the open stage columns; Pipeline Value = Board pipeline amount; Avg Probability = mean probability of the open cards (±0.5) | I6: As expected | J6: Data | K6: High | L6: Pass | N6: tests/opportunities/view.spec.ts
A7: OPP-006 | B7: UC-OPP-001 | C7: View Opportunities | D7: Pagination covers every opportunity | E7: Logged in as CRM Administrator | F7: 1. Open /opportunities; read "Showing 1–20 of N opportunities · Page 1 of M" 2. Click Next, then Previous 3. Sort Created Date oldest first and click Next until the last page, counting the rows | H7: N = Total card; Previous disabled on page 1; Next shows rows 21–40 (page 2); Previous returns to page 1; the last page ends at N and Next is disabled there; N rows in all, none listed twice | I7: As expected | J7: Functional | K7: High | L7: Pass | N7: tests/opportunities/view.spec.ts
A8: OPP-007 | B8: UC-OPP-001 | C8: View Opportunities | D8: Board view shows one column per stage | E8: Logged in as CRM Administrator | F8: 1. Open /opportunities 2. Click Board 3. Compare the columns with the configured opportunity stages (reference data OPPORTUNITY / STAGE) 4. Click List | H8: Board is pressed; columns Qualified, Site Visit, Negotiation, Reservation Ready, Proposal, Won, Lost; every configured stage except Open has a column; List brings the table back | I8: As expected | J8: UI | K8: Medium | L8: Pass | N8: tests/opportunities/view.spec.ts
A9: OPP-008 | B9: UC-OPP-001 | C9: View Opportunities | D9: Viewing does not change data | E9: Logged in as CRM Administrator | F9: 1. Open /opportunities with the browser network log open 2. Sort by Budget 3. Open a record and close it 4. Switch to Board and back to List | H9: No create / update / delete request (POST, PUT, PATCH, DELETE) to opportunity, lead, visit, note, reservation, contract or unit-hold endpoints | I9: As expected | J9: Functional | K9: High | L9: Pass | N9: tests/opportunities/view.spec.ts
A10: OPP-009 | B10: UC-OPP-002 | C10: Create Opportunity | D10: Converting a qualified lead creates an opportunity | E10: Logged in as CRM Administrator; a lead on Leads › Ready to Convert (picked by OPP-046) | F10: 1. Open Leads, search the lead number and open it 2. Click "Move to Opportunity" 3. Click Convert 4. Click OK on the notice | G10: A Qualified lead picked at random from Ready to Convert page 1 | H10: POST /leads/<id>/convert succeeds; notice "Lead Converted" names the customer; the Opportunity Detail of the new OPP-… number opens on /opportunities | I10: As expected | J10: Functional | K10: High | L10: Pass | N10: tests/opportunities/lifecycle.spec.ts
A11: OPP-010 | B11: UC-OPP-002 | C11: Create Opportunity | D11: New opportunity is listed and searchable | E11: Logged in as CRM Administrator; the opportunity created by OPP-009 in this run | F11: 1. Open /opportunities (newest first) 2. Look for the new OPP number on page 1 3. Search the OPP number | G11: OPP number from OPP-009 | H11: The new opportunity is on page 1 and searching its number lists exactly that opportunity | I11: As expected | J11: Functional | K11: High | L11: Pass | N11: tests/opportunities/lifecycle.spec.ts
A12: OPP-011 | B12: UC-OPP-002 | C12: Create Opportunity | D12: Customer, budget and lead number carry over from the lead | E12: Logged in as CRM Administrator; the opportunity created by OPP-009 in this run | F12: 1. Note the lead's name, Budget and number in Lead Detail (before converting) 2. Open the new opportunity 3. Compare the detail header | H12: The opportunity shows the lead's customer name, budget and lead number | I12: As expected | J12: Data | K12: High | L12: Pass | N12: tests/opportunities/lifecycle.spec.ts
A13: OPP-012 | B13: UC-OPP-002 | C13: Create Opportunity | D13: New opportunity starts at Qualified | E13: Logged in as CRM Administrator; the opportunity created by OPP-009 in this run | F13: 1. Open the new opportunity 2. Read the status, Probability and Workflow Status 3. Compare the probability with other Qualified rows on page 1 and the owner with the lead's Assigned user | H13: Stage Qualified, status OPEN, probability as configured for Qualified (same as other Qualified deals), owner = the lead's assignee; workflow shows Open Done, Qualified In progress, later steps Up next | I13: As expected | J13: Functional | K13: High | L13: Pass | N13: tests/opportunities/lifecycle.spec.ts
A14: OPP-013 | B14: UC-OPP-002 | C14: Create Opportunity | D14: Total and Open KPIs go up by one | E14: Logged in as CRM Administrator; the opportunity created by OPP-009 in this run | F14: 1. Before converting, note Total and Open on /opportunities 2. Convert the lead (OPP-009) 3. Open /opportunities again and read Total and Open | H14: Total and Open each increase by exactly 1 | I14: As expected | J14: Data | K14: High | L14: Pass | N14: tests/opportunities/lifecycle.spec.ts
A15: OPP-014 | B15: UC-OPP-002 | C15: Create Opportunity | D15: Board Qualified column takes the new deal | E15: Logged in as CRM Administrator; the opportunity created by OPP-009 in this run | F15: 1. Before converting, note the Board › Qualified count and value 2. Convert the lead (OPP-009) 3. Open the Board again | H15: Board › Qualified: count +1 and value + the opportunity's budget (within display rounding) | I15: As expected | J15: Data | K15: High | L15: Pass | N15: tests/opportunities/lifecycle.spec.ts
A16: OPP-015 | B16: UC-OPP-002 | C16: Create Opportunity | D16: Board card shows the new opportunity | E16: Logged in as CRM Administrator; the opportunity created by OPP-009 in this run | F16: 1. Open /opportunities › Board 2. Find the card with the new OPP number in Qualified | H16: The card shows the customer, the lead's budget, a probability tag and the owner (the lead's assignee) | I16: As expected | J16: UI | K16: Medium | L16: Pass | N16: tests/opportunities/lifecycle.spec.ts
A17: OPP-016 | B17: UC-OPP-002 | C17: Create Opportunity | D17: Only one opportunity is created per conversion | E17: Logged in as CRM Administrator; the opportunity created by OPP-009 in this run | F17: 1. Search the lead number on /opportunities 2. Run the same search through the API (GET /opportunities?search=<lead number>) | G17: Lead number from OPP-046 | H17: Exactly one opportunity — the new one — for the lead | I17: As expected | J17: Negative | K17: High | L17: Pass | N17: tests/opportunities/lifecycle.spec.ts
A18: OPP-017 | B18: UC-OPP-002 | C18: Create Opportunity | D18: Lead link in the opportunity opens the source lead | E18: Logged in as CRM Administrator; the opportunity created by OPP-009 in this run | F18: 1. Open the new opportunity 2. Click the LEAD number in the header | H18: Lead Detail of that lead opens | I18: As expected | J18: Navigation | K18: Medium | L18: Pass | N18: tests/opportunities/lifecycle.spec.ts
A19: OPP-018 | B19: UC-OPP-002 | C19: Create Opportunity | D19: A lead that is not qualified cannot be converted | E19: Logged in as CRM Administrator | F19: 1. Open Leads › To Qualify 2. Open a lead whose status is not Qualified (e.g. Assigned) | G19: First lead on To Qualify that is not Qualified | H19: Lead Detail does not offer "Move to Opportunity" | I19: As expected | J19: Negative | K19: High | L19: Pass | N19: tests/opportunities/view.spec.ts
A20: OPP-019 | B20: UC-OPP-003 | C20: View Opportunity Details | D20: Opening a record shows its details | E20: Logged in as CRM Administrator | F20: 1. Open /opportunities 2. Click the first OPP number 3. Compare the detail header with the list row (and GET /opportunities/<id>) 4. Close the detail and open the second row | H20: Opportunity Detail shows the same number, customer, lead, stage, probability and budget as the row and the API record; opening it does not modify the record; the second record opens after closing the first | I20: As expected | J20: Functional | K20: High | L20: Pass | N20: tests/opportunities/view.spec.ts
A21: OPP-020 | B21: UC-OPP-004 | C21: Edit Opportunity | D21: Opportunity fields can be edited | E21: Logged in as CRM Administrator | F21: 1. Open an open opportunity 2. Look for an Edit action for Budget, Probability, Expected Close and Project 3. Change a value and save 4. Reopen the record | H21: Budget, probability, expected close and project can be edited, saved and are shown when the record is reopened | I21: Not testable: the app has no edit form; these fields change only through workflow actions (visits, negotiation, reservation) | J21: Functional | K21: High | L21: Blocked | N21: tests/opportunities/view.spec.ts (skipped)
A22: OPP-021 | B22: UC-OPP-004 | C22: Edit Opportunity | D22: Add Note saves a note on the opportunity | E22: Logged in as CRM Administrator; the opportunity created by OPP-009 in this run | F22: 1. Open the test opportunity 2. Type a note in Add Note › Note 3. Click Add Note | G22: "Automated test - Opportunities lifecycle note <timestamp>" | H22: The note appears under Notes; the stage does not change | I22: As expected | J22: Functional | K22: High | L22: Pass | N22: tests/opportunities/lifecycle.spec.ts
A23: OPP-022 | B23: UC-OPP-004 | C23: Edit Opportunity | D23: An empty note is not saved | E23: Logged in as CRM Administrator; the opportunity created by OPP-009 in this run | F23: 1. Open the test opportunity 2. Leave Add Note › Note empty 3. Click Add Note | G23: Empty note | H23: No request is sent and the user is told a note is needed (message, notice or disabled button) | I23: As expected | J23: Negative | K23: Medium | L23: Pass | N23: tests/opportunities/lifecycle.spec.ts
A24: OPP-023 | B24: UC-OPP-004 | C24: Edit Opportunity | D24: Visit date cannot be in the past | E24: Logged in as CRM Administrator; the opportunity created by OPP-009 in this run | F24: 1. Open the test opportunity (Qualified) 2. Click Visit Date in "Schedule Visit & Continue" | H24: In the date picker every day before today is disabled and today can be picked | I24: As expected | J24: Negative | K24: Medium | L24: Pass | N24: tests/opportunities/lifecycle.spec.ts
A25: OPP-024 | B25: UC-OPP-003, UC-OPP-004 | C25: View Opportunity Details / Edit Opportunity | D25: Record link (?selected=id) opens and keeps the record open | E25: Logged in as CRM Administrator | F25: 1. Copy the link of a row (/opportunities?selected=<id>) 2. Open the link in the browser 3. Wait 3 seconds | H25: That opportunity's detail opens and stays open until closed | I25: As expected | J25: Navigation | K25: High | L25: Pass | N25: tests/opportunities/view.spec.ts
A26: OPP-025 | B26: UC-OPP-004 | C26: Edit Opportunity | D26: Saved changes persist after reopening | E26: Logged in as CRM Administrator; the opportunity created by OPP-009 in this run | F26: 1. Reload /opportunities 2. Open the test opportunity again 3. Look at Notes and Site Visits | H26: The note (OPP-021) and the site visit (OPP-038) are still shown | I26: As expected | J26: Functional | K26: High | L26: Pass | N26: tests/opportunities/lifecycle.spec.ts
A27: OPP-026 | B27: UC-OPP-004, UC-OPP-012 | C27: Edit Opportunity / Validate Role-Based Access | D27: A closed opportunity offers no workflow actions | E27: Logged in as CRM Administrator; the test opportunity marked Lost by OPP-040 | F27: 1. Open the Lost opportunity 2. Review the action panels | H27: Lost reason / by / on shown read-only; "Marked Lost" disabled; no visit or stage actions; Unit Hold says "This opportunity is closed, so units cannot be held." | I27: As expected | J27: Security | K27: High | L27: Pass | N27: tests/opportunities/lifecycle.spec.ts
A28: OPP-027 | B28: UC-OPP-005 | C28: Search Opportunity | D28: Search by opportunity number | E28: Logged in as CRM Administrator | F28: 1. Open /opportunities 2. Note the 4th row 3. Type its OPP number in "Search opportunity, customer, lead, project" | G28: OPP number of the 4th row | H28: Exactly the matching opportunity is listed, with the same values as before searching | I28: As expected | J28: Functional | K28: High | L28: Pass | N28: tests/opportunities/search-sort.spec.ts
A29: OPP-028 | B29: UC-OPP-005 | C29: Search Opportunity | D29: Search by customer name and by lead number | E29: Logged in as CRM Administrator | F29: 1. Open /opportunities 2. Search the customer name of the 2nd row 3. Search the lead number of the 2nd row | G29: Customer and LD number of the 2nd row | H29: Customer search: every row matches the term (number, lead, customer or project) and includes the 2nd row; lead search: only that lead's opportunity | I29: As expected | J29: Functional | K29: High | L29: Pass | N29: tests/opportunities/search-sort.spec.ts
A30: OPP-029 | B30: UC-OPP-005 | C30: Search Opportunity | D30: Search with no match shows the empty state | E30: Logged in as CRM Administrator | F30: 1. Open /opportunities 2. Search a term that matches nothing | G30: "zz-no-such-opportunity-<timestamp>" | H30: "No opportunities found." and Export disabled | I30: As expected | J30: Negative | K30: Medium | L30: Pass | N30: tests/opportunities/search-sort.spec.ts
A31: OPP-030 | B31: UC-OPP-005 | C31: Search Opportunity | D31: Clearing the search restores the list | E31: Logged in as CRM Administrator | F31: 1. Open /opportunities; note the total and page 1 2. Search the first row's customer 3. Click the clear (×) button in the search box | G31: Customer of the first row | H31: The search narrows the list; after clearing, the box is empty and the total and page 1 are as before | I31: As expected | J31: Functional | K31: Medium | L31: Pass | N31: tests/opportunities/search-sort.spec.ts
A32: OPP-031 | B32: UC-OPP-005 | C32: Search Opportunity | D32: Search ignores letter case | E32: Logged in as CRM Administrator | F32: 1. Open /opportunities 2. Search a mixed-case customer name as shown, in UPPER CASE and in lower case | G32: A customer name from page 1 | H32: All three searches return the same opportunities | I32: As expected | J32: Functional | K32: Medium | L32: Pass | N32: tests/opportunities/search-sort.spec.ts
A33: OPP-032 | B33: UC-OPP-006 | C33: Filter and Sort Opportunities | D33: Sort by Budget | E33: Logged in as CRM Administrator | F33: 1. Open /opportunities 2. Click the Budget header until it sorts ascending; check page 1 and the first rows of page 2 3. Repeat for descending | H33: Budget sorts ascending and descending by the amount shown, the header shows the direction, and the order continues across pages | I33: Not in shown-amount order: ascending lists "1M USD" before "7,738.14 USD" — the sort seems to use the unconverted budget, not the USD amount shown | J33: Functional | K33: Medium | L33: Fail | N33: tests/opportunities/search-sort.spec.ts
A34: OPP-033 | B34: UC-OPP-006 | C34: Filter and Sort Opportunities | D34: Sort by Created Date | E34: Logged in as CRM Administrator | F34: 1. Open /opportunities 2. Check the default order 3. Click the Created Date header until it sorts ascending | H34: Default is newest first (Created Date ▼); ascending gives oldest first | I34: As expected | J34: Functional | K34: Medium | L34: Pass | N34: tests/opportunities/search-sort.spec.ts
A35: OPP-034 | B35: UC-OPP-006 | C35: Filter and Sort Opportunities | D35: Sort by Probability and Customer | E35: Logged in as CRM Administrator | F35: 1. Open /opportunities 2. Sort Probability ascending, then descending 3. Sort Customer ascending, then descending | H35: Probability sorts numerically and Customer alphabetically (letters and digits; spaces and punctuation ignored, as the database does), both directions | I35: As expected | J35: Functional | K35: Medium | L35: Pass | N35: tests/opportunities/search-sort.spec.ts
A36: OPP-035 | B36: UC-OPP-006 | C36: Filter and Sort Opportunities | D36: Board Owner filter | E36: Logged in as CRM Administrator | F36: 1. Open /opportunities › Board; note the column counts 2. Choose each owner in turn (up to two with deals) 3. Choose "All owners" | G36: Owners listed in the Owner filter | H36: Only that owner's cards are shown and no column count rises; "All owners" gives the same board as a freshly loaded one | I36: As expected | J36: Functional | K36: Medium | L36: Pass | N36: tests/opportunities/search-sort.spec.ts
A37: OPP-036 | B37: UC-OPP-006 | C37: Filter and Sort Opportunities | D37: Board Project filter | E37: Logged in as CRM Administrator | F37: 1. Open /opportunities › Board; note the column counts 2. Choose a project that has deals 3. Check each card's project (opportunity record) 4. Choose "All projects" | G37: Projects listed in the Project filter | H37: Only cards of that project are shown and no column count rises; "All projects" gives the same board as a freshly loaded one | I37: As expected | J37: Functional | K37: Medium | L37: Pass | N37: tests/opportunities/search-sort.spec.ts
A38: OPP-037 | B38: UC-OPP-006 | C38: Filter and Sort Opportunities | D38: Board closed-deals window | E38: Logged in as CRM Administrator | F38: 1. Open /opportunities › Board 2. Choose Won / Lost: last 30 days, last 90 days, this year and all time in turn 3. Note the Won, Lost and open column counts each time | H38: Won/Lost counts never shrink from 30 days → 90 days → all time, and this year ≤ all time; open columns do not change | I38: As expected | J38: Functional | K38: Medium | L38: Pass | N38: tests/opportunities/search-sort.spec.ts
A39: OPP-038 | B39: UC-OPP-007 | C39: Change Opportunity Stage | D39: Scheduling the first visit moves Qualified → Site Visit | E39: Logged in as CRM Administrator; the test opportunity at Qualified | F39: 1. Open the test opportunity 2. Visit Type: Virtual 3. Visit Date: next month, the 15th, time 11:00, click Set 4. Enter Visit Remarks 5. Click "Schedule Visit & Continue", then OK 6. Reload; check the list row, the detail and the Site Visits section | G39: Virtual; 15th of next month 11:00; remarks "Automated test - Opportunities lifecycle" | H39: Notice "Site Visit Saved"; stage Site Visit in the detail, the list and the API; probability rises; the visit is listed as "Virtual · Scheduled" with the chosen date and time 11:00 | I39: Stage moves to Site Visit as expected, but the picked time 11:00 is shown as "15 Nov 2026, 22:30" (saved as 17:00 UTC; browser on India time) | J39: Functional | K39: High | L39: Fail | N39: tests/opportunities/lifecycle.spec.ts
A40: OPP-039 | B40: UC-OPP-008 | C40: Mark Opportunity as Won | D40: A Won opportunity is recorded as Won | E40: Logged in as CRM Administrator | F40: 1. Open /opportunities 2. Open the first opportunity whose stage is Won 3. Review the status, probability, workflow and action panels | G40: First Won opportunity in the list | H40: Status Won (API status WON), probability 100%, every workflow step Done, no stage-advancing actions | I40: As expected. Observation: the Won record still offers "Mark Lost" (see OBS-06) | J40: Functional | K40: High | L40: Pass | N40: tests/opportunities/view.spec.ts
A41: OPP-040 | B41: UC-OPP-009 | C41: Mark Opportunity as Lost | D41: Mark Lost requires a reason, can be cancelled, and records the loss | E41: Logged in as CRM Administrator; the test opportunity at Site Visit | F41: 1. Note Open on /opportunities; open the test opportunity 2. Mark Lost with no reason 3. Choose a reason and remarks, click Mark Lost, then Go back 4. Click Mark Lost again, then Confirm, then OK 5. Close the detail; reload the list | G41: Lost Reason "No Decision"; remarks "Automated test - Opportunities lifecycle" | H41: No reason → "Required Fields Missing • Lost Reason"; Go back sends nothing and the deal stays open; Confirm → notice "Opportunity Lost", status Lost, probability 0%, reason / remarks / marked-lost-by shown, list row Lost, Open card −1 | I41: As expected | J41: Functional | K41: High | L41: Pass | N41: tests/opportunities/lifecycle.spec.ts
A42: OPP-041 | B42: UC-OPP-008, UC-OPP-009 | C42: Mark Opportunity as Won / Mark Opportunity as Lost | D42: A closed opportunity cannot change stage again | E42: Logged in as CRM Administrator; the test opportunity marked Lost by OPP-040 | F42: 1. Open /opportunities › Board; expand Won and Lost ("Show") 2. Check the cards for a "Move / mark Lost" menu 3. Send POST /opportunities/<id>/stage moving the Lost opportunity back to Qualified | G42: Stage ref id of Qualified | H42: Lost cards have no move menu, and the backend refuses the stage change (4xx); the opportunity stays Lost | I42: As expected for Lost. Observation: Won cards still offer moves (see OBS-06) | J42: Security | K42: High | L42: Pass | N42: tests/opportunities/lifecycle.spec.ts
A43: OPP-042 | B43: UC-OPP-007 | C43: Change Opportunity Stage | D43: Visit without a date is rejected | E43: Logged in as CRM Administrator; the test opportunity at Qualified | F43: 1. Open the test opportunity 2. Click "Schedule Visit & Continue" without choosing a Visit Date | G43: Visit Date empty | H43: "Select a visit date and time." and no request is sent | I43: As expected | J43: Negative | K43: High | L43: Pass | N43: tests/opportunities/lifecycle.spec.ts
A44: OPP-043 | B44: UC-OPP-007 | C44: Change Opportunity Stage | D44: Board only offers moves the workflow allows | E44: Logged in as CRM Administrator; the test opportunity at Site Visit | F44: 1. Open /opportunities › Board 2. Open the "Move / mark Lost…" menu on the test opportunity's card 3. Choose an option marked "(not from board)" if it can be chosen | H44: Moves marked "(not from board)" are disabled, and choosing one does not change the stage | I44: The "(not from board)" options (Qualified, Negotiation, Reservation Ready, Proposal, Won) can be selected; choosing one did not change the stage | J44: Negative | K44: Medium | L44: Fail | N44: tests/opportunities/lifecycle.spec.ts
A45: OPP-044 | B45: UC-OPP-007 | C45: Change Opportunity Stage | D45: Backend rejects a prohibited stage change | E45: Logged in as CRM Administrator; the test opportunity at Site Visit | F45: 1. Send POST /opportunities/<id>/stage with the Won stage, probability 100 2. Read the opportunity again | G45: Stage ref id of Won | H45: The backend refuses the change (4xx) and the stage stays Site Visit | I45: As expected | J45: Security | K45: High | L45: Pass | N45: tests/opportunities/lifecycle.spec.ts
A46: OPP-045 | B46: UC-OPP-007 | C46: Change Opportunity Stage | D46: Workflow and stage history follow the stage | E46: Logged in as CRM Administrator; the test opportunity at Site Visit | F46: 1. Open the test opportunity 2. Read Workflow Status 3. Read the stage history (GET /opportunities/<id>) | H46: Open and Qualified Done, Site Visit In progress, later steps Up next; stage history lists Qualified then Site Visit | I46: As expected | J46: Functional | K46: Medium | L46: Pass | N46: tests/opportunities/lifecycle.spec.ts
A47: OPP-046 | B47: UC-OPP-010 | C47: Convert Lead to Opportunity | D47: Ready to Convert lists only qualified leads | E47: Logged in as CRM Administrator | F47: 1. Open Leads 2. Click the "Ready to Convert" tab 3. Check every lead's status and compare the tab count with the pager total | H47: Every lead on the tab has status Qualified, and the tab count equals the list total | I47: As expected | J47: Functional | K47: High | L47: Pass | N47: tests/opportunities/lifecycle.spec.ts
A48: OPP-047 | B48: UC-OPP-010 | C48: Convert Lead to Opportunity | D48: Move to Opportunity asks for confirmation | E48: Logged in as CRM Administrator; the lead picked by OPP-046 | F48: 1. Open the lead 2. Click "Move to Opportunity" | H48: A "Convert lead to opportunity?" dialog names the lead and offers Go back and Convert | I48: As expected | J48: UI | K48: High | L48: Pass | N48: tests/opportunities/lifecycle.spec.ts
A49: OPP-048 | B49: UC-OPP-010 | C49: Convert Lead to Opportunity | D49: Go back cancels the conversion | E49: Logged in as CRM Administrator; the lead picked by OPP-046 | F49: 1. Open the lead 2. Click "Move to Opportunity" 3. Click Go back | H49: The dialog closes, no request is sent, the lead stays Qualified and "Move to Opportunity" is still offered | I49: As expected | J49: Negative | K49: High | L49: Pass | N49: tests/opportunities/lifecycle.spec.ts
A50: OPP-049 | B50: UC-OPP-010 | C50: Convert Lead to Opportunity | D50: Converted lead is closed as Converted | E50: Logged in as CRM Administrator; the lead converted by OPP-009 | F50: 1. Open the converted lead 2. Read its status and Status History | H50: Lead status Converted; Status History shows "Qualified → Converted" | I50: As expected | J50: Functional | K50: High | L50: Pass | N50: tests/opportunities/lifecycle.spec.ts
A51: OPP-050 | B51: UC-OPP-010 | C51: Convert Lead to Opportunity | D51: Ready to Convert count goes down by one | E51: Logged in as CRM Administrator; the lead converted by OPP-009 | F51: 1. Before converting, note the Ready to Convert tab count 2. Convert the lead (OPP-009) 3. Open Leads again and read the count | H51: The Ready to Convert count decreases by exactly 1 | I51: As expected | J51: Data | K51: High | L51: Pass | N51: tests/opportunities/lifecycle.spec.ts
A52: OPP-051 | B52: UC-OPP-010 | C52: Convert Lead to Opportunity | D52: Converted lead links to its opportunity | E52: Logged in as CRM Administrator; the lead converted by OPP-009 | F52: 1. Open the converted lead 2. Read the OPPORTUNITIES field and the action panel | H52: The lead shows the new OPP number under Opportunities and no longer offers "Move to Opportunity" | I52: As expected | J52: Functional | K52: High | L52: Pass | N52: tests/opportunities/lifecycle.spec.ts
A53: OPP-052 | B53: UC-OPP-010 | C53: Convert Lead to Opportunity | D53: Converting the same lead again is refused | E53: Logged in as CRM Administrator; the lead converted by OPP-009 | F53: 1. Send POST /leads/<id>/convert again for the converted lead 2. Search opportunities by the lead number | G53: probabilityPercent 35, remarks "… (repeat conversion)" | H53: Refused (4xx), or answered with the existing opportunity; either way there is still exactly one opportunity for the lead | I53: Pass: the API answers 201 with the existing opportunity (no duplicate created) — see OBS-10 | J53: Negative | K53: High | L53: Pass | N53: tests/opportunities/lifecycle.spec.ts
A54: OPP-053 | B54: UC-OPP-010 | C54: Convert Lead to Opportunity | D54: Conversion is traceable on both records | E54: Logged in as CRM Administrator; the opportunity created by OPP-009 | F54: 1. Read the opportunity (GET /opportunities/<id>) 2. Compare its first stage-history entry with Created by / Created at and the lead reference | H54: The first stage is Qualified, set by the converting user at creation time (within a minute); the lead reference is the converted lead | I54: As expected | J54: Data | K54: Medium | L54: Pass | N54: tests/opportunities/lifecycle.spec.ts
A55: OPP-054 | B55: UC-OPP-011 | C55: Delete Opportunity | D55: Delete is not offered in the UI | E55: Logged in as CRM Administrator | F55: 1. Open /opportunities and look for a Delete / Remove / Archive / Deactivate action 2. Open a record and look again 3. Open the Board and check a card's move menu | H55: List, board and detail have no Delete action (policy to confirm: closing as Lost replaces deletion — see OBS-09) | I55: As expected | J55: Functional | K55: Medium | L55: Pass | N55: tests/opportunities/view.spec.ts
A56: OPP-055 | B56: UC-OPP-011 | C56: Delete Opportunity | D56: Backend does not delete an opportunity | E56: Logged in as CRM Administrator; the test opportunity marked Lost by OPP-040 | F56: 1. Send DELETE /opportunities/<id> with a valid login 2. Read the opportunity again | H56: The DELETE is refused (4xx) and the record is still returned and active | I56: As expected | J56: Security | K56: High | L56: Pass | N56: tests/opportunities/lifecycle.spec.ts
A57: OPP-056 | B57: UC-OPP-011 | C57: Delete Opportunity | D57: A closed (Lost) opportunity stays on record | E57: Logged in as CRM Administrator; the test opportunity marked Lost by OPP-040 | F57: 1. Search the OPP number on /opportunities 2. Open it | H57: The Lost opportunity is still listed (stage Lost), searchable and opens as Lost | I57: As expected | J57: Functional | K57: Medium | L57: Pass | N57: tests/opportunities/lifecycle.spec.ts
A58: OPP-057 | B58: UC-OPP-011, UC-OPP-012 | C58: Delete Opportunity / Validate Role-Based Access | D58: Backend rejects requests without a valid login | E58: None (requests sent without a login) | F58: 1. Send GET /opportunities, GET /opportunities/<id>, DELETE /opportunities/<id> and POST /opportunities/<id>/stage without a token 2. Repeat GET and DELETE with an invalid token | G58: Record id 00000000-0000-0000-0000-000000000000 (matches nothing) | H58: Every call returns 401 | I58: As expected | J58: Security | K58: High | L58: Pass | N58: tests/opportunities/access.spec.ts
A59: OPP-058 | B59: UC-OPP-012 | C59: Validate Role-Based Access | D59: Signed-out user is sent to the login page | E59: Not logged in (new browser session) | F59: 1. Open /opportunities | H59: Redirected to /login; no opportunity data shown | I59: As expected | J59: Security | K59: High | L59: Pass | N59: tests/opportunities/access.spec.ts
A60: OPP-059 | B60: UC-OPP-012 | C60: Validate Role-Based Access | D60: Each role sees only permitted records and actions | E60: Test accounts for each role (e.g. Sales Executive, Sales Manager, Lead Reviewer) | F60: 1. Log in as each role 2. Open /opportunities and compare the records listed 3. Try an action the role may not perform, in the UI and through the API | G60: One account per role | H60: Sales users see only their records; restricted actions are hidden or disabled and refused by the backend | I60: Not testable yet: only the CRM Administrator login is configured | J60: Security | K60: High | L60: Blocked | N60: tests/opportunities/access.spec.ts (skipped)
A61: OPP-060 | B61: UC-OPP-003 | C61: View Opportunity Details | D61: Link to a missing opportunity shows a message | E61: Logged in as CRM Administrator | F61: 1. Open /opportunities?selected=<id that does not exist> | G61: 00000000-0000-0000-0000-000000000000 | H61: A message says the opportunity was not found (no endless loading, no silent close) | I61: The detail window opens on "Loading opportunity details..." and closes after about a second with no message | J61: Negative | K61: Medium | L61: Fail | N61: tests/opportunities/view.spec.ts
A62: OPP-061 | B62: UC-OPP-001 | C62: View Opportunities | D62: Board view shows its toolbar, hint and stage columns | E62: Logged in as CRM Administrator | F62: 1. Open /opportunities 2. Click Board | H62: Filters "All owners", "All projects", "Won / Lost: last 30 days"; the summary "Open pipeline: N deals · amount · weighted amount"; the hint "Drag a card or use "Move / mark Lost…"…"; columns Qualified, Site Visit, Negotiation, Reservation Ready, Proposal, Won, Lost; Search and Export stay available | I62: As expected | J62: UI | K62: High | L62: Pass | N62: tests/opportunities/board.spec.ts
A63: OPP-062 | B63: UC-OPP-001 | C63: View Opportunities | D63: Board column headers add up their cards | E63: Logged in as CRM Administrator | F63: 1. Open the Board 2. For each open stage read the count, value and "Weighted" value 3. Add up the cards of that column (value, and value × probability) | H63: Count = number of cards; value = sum of the card values; weighted = sum of value × probability (each within display rounding) | I63: As expected | J63: Data | K63: High | L63: Pass | N63: tests/opportunities/board.spec.ts
A64: OPP-063 | B64: UC-OPP-001 | C64: View Opportunities | D64: Board summary equals the open columns | E64: Logged in as CRM Administrator | F64: 1. Open the Board 2. Read "Open pipeline: N deals · amount · weighted amount" 3. Add up the open stage columns | H64: Deals = sum of the open column counts; amount = sum of their values; weighted = sum of their weighted values (within rounding) | I64: As expected | J64: Data | K64: High | L64: Pass | N64: tests/opportunities/board.spec.ts
A65: OPP-064 | B65: UC-OPP-001 | C65: View Opportunities | D65: Board cards show the deal at a glance | E65: Logged in as CRM Administrator | F65: 1. Open the Board 2. Look at the cards of the open stages | H65: Every card shows customer, budget, OPP number, probability (%), "Nd in stage", owner and a "Move / mark Lost…" menu | I65: As expected | J65: UI | K65: Medium | L65: Pass | N65: tests/opportunities/board.spec.ts
A66: OPP-065 | B66: UC-OPP-001 | C66: View Opportunities | D66: Board cards match the List | E66: Logged in as CRM Administrator | F66: 1. Open the Board; note up to 3 cards of each open stage 2. Search each OPP number in the List view | G66: Up to 3 cards per open stage | H66: Customer, budget and probability are the same as the List row, and the card sits in the column of the row's stage | I66: As expected | J66: Data | K66: High | L66: Pass | N66: tests/opportunities/board.spec.ts
A67: OPP-066 | B67: UC-OPP-001 | C67: View Opportunities | D67: "Days in stage" and the stale highlight | E67: Logged in as CRM Administrator | F67: 1. Open the Board 2. For up to 5 cards compare "Nd in stage" with the last stage change (stage history) 3. Compare highlighted (red) and plain "in stage" tags | H67: "Nd in stage" = whole days since the last stage change (±1); every highlighted card has been in its stage longer than every plain one | I67: As expected | J67: Data | K67: Medium | L67: Pass | N67: tests/opportunities/board.spec.ts
A68: OPP-067 | B68: UC-OPP-001 | C68: View Opportunities | D68: "Reserved" tag shows deals with an active reservation | E68: Logged in as CRM Administrator | F68: 1. Open the Board 2. For up to 5 cards with "Reserved" and up to 5 without it in Reservation Ready, check the opportunity's reservations | H68: "Reserved" cards have a Requested or Approved reservation; cards without the tag have none | I68: As expected | J68: Data | K68: Medium | L68: Pass | N68: tests/opportunities/board.spec.ts
A69: OPP-068 | B69: UC-OPP-003 | C69: View Opportunity Details | D69: Opening a card shows the opportunity | E69: Logged in as CRM Administrator | F69: 1. Open the Board 2. Click a card 3. Close the detail, focus the card and press Enter | G69: First card in Qualified | H69: Both open the Opportunity Detail of that card's opportunity | I69: As expected | J69: Navigation | K69: High | L69: Pass | N69: tests/opportunities/board.spec.ts
A70: OPP-069 | B70: UC-OPP-005 | C70: Search Opportunity | D70: Search filters the Board | E70: Logged in as CRM Administrator | F70: 1. Open the Board 2. Search a customer name 3. Clear the search | G70: Customer of a Reservation Ready card | H70: Only that customer's cards remain; column counts and the summary follow the search; clearing it restores the board | I70: As expected | J70: Functional | K70: High | L70: Pass | N70: tests/opportunities/board.spec.ts
A71: OPP-070 | B71: UC-OPP-001 | C71: View Opportunities | D71: Export from the Board follows the search | E71: Logged in as CRM Administrator | F71: 1. Open the Board 2. Search a customer name 3. Click Export | G71: Customer of a Reservation Ready card | H71: A file "opportunities-<today>.xlsx" downloads with the opportunity columns (Opportunity No, Customer, Lead No, Stage, Status, …) holding exactly the opportunities the search finds | I71: As expected | J71: Functional | K71: Medium | L71: Pass | N71: tests/opportunities/board.spec.ts
A72: OPP-071 | B72: UC-OPP-006 | C72: Filter and Sort Opportunities | D72: Won and Lost columns open and close | E72: Logged in as CRM Administrator | F72: 1. Open the Board 2. Look at Won and Lost 3. Click Show, then Hide 4. Choose "Won / Lost: last 90 days" | H72: Won and Lost say "Closed last 30 days"; a collapsed column offers Show and lists no cards, Show lists its cards (as many as the count, up to 50) and turns into Hide, Hide collapses it again (the choice is remembered per user); the header follows the window ("Closed last 90 days") | I72: As expected | J72: Functional | K72: Medium | L72: Pass | N72: tests/opportunities/board.spec.ts
A73: OPP-072 | B73: UC-OPP-007 | C73: Change Opportunity Stage | D73: Card menu lists the possible moves | E73: Logged in as CRM Administrator | F73: 1. Open the Board 2. Open the "Move / mark Lost…" menu of cards in each open stage | G73: First card of each open stage | H73: The menu never offers the card's own stage; it always offers Lost; Won is marked "(not from board)" | I73: As expected | J73: Functional | K73: Medium | L73: Pass | N73: tests/opportunities/board.spec.ts
A74: OPP-073 | B74: UC-OPP-009 | C74: Mark Opportunity as Lost | D74: Mark as Lost from a card can be cancelled | E74: Logged in as CRM Administrator | F74: 1. Open the Board 2. Choose "Lost" in a card's menu 3. Look at the dialog, then click Cancel | G74: First card in Qualified | H74: Dialog "Mark as Lost" with Lost Reason (Price, Funding Issue, Competitor, No Decision, Timing), Remarks, Cancel and Continue; Cancel closes it, sends nothing and leaves the card in its column | I74: As expected | J74: Negative | K74: Medium | L74: Pass | N74: tests/opportunities/board.spec.ts
A75: OPP-074 | B75: UC-OPP-002 | C75: Create Opportunity | D75: A newly converted opportunity appears on the Board | E75: Logged in as CRM Administrator; a lead on Leads › Ready to Convert | F75: 1. Note the Qualified count on the Board 2. Convert a Ready to Convert lead (Move to Opportunity › Convert) 3. Open the Board | G75: A Qualified lead picked at random | H75: The new card is in Qualified with "35%" (or the configured probability), "0d in stage" and the lead's owner; Qualified count +1 | I75: As expected | J75: Functional | K75: High | L75: Pass | N75: tests/opportunities/lifecycle.spec.ts
A76: OPP-075 | B76: UC-OPP-007 | C76: Change Opportunity Stage | D76: Dragging a card to a stage the workflow does not allow is refused | E76: Logged in as CRM Administrator; the board test opportunity (Qualified) from OPP-074 | F76: 1. Open the Board 2. Drag the test card from Qualified onto Negotiation | H76: Message "Can't move to Negotiation — Complete a site visit with outcome notes to move to Negotiation." with Close and Open opportunity; the stage stays Qualified and the card stays in Qualified | I76: As expected | J76: Negative | K76: High | L76: Pass | N76: tests/opportunities/lifecycle.spec.ts
A77: OPP-076 | B77: UC-OPP-009 | C77: Mark Opportunity as Lost | D77: Dropping a card on Lost asks for the loss details | E77: Logged in as CRM Administrator; the board test opportunity (Qualified) from OPP-074 | F77: 1. Open the Board 2. Drag the test card onto the Lost column 3. Click Cancel | H77: The "Mark as Lost" dialog opens; Cancel leaves the opportunity Qualified | I77: As expected | J77: Functional | K77: Medium | L77: Pass | N77: tests/opportunities/lifecycle.spec.ts
A78: OPP-077 | B78: UC-OPP-009 | C78: Mark Opportunity as Lost | D78: Mark as Lost from the Board needs a reason | E78: Logged in as CRM Administrator; the board test opportunity (Qualified) from OPP-074 | F78: 1. Choose "Lost" in the test card's menu 2. Click Continue without a Lost Reason | G78: Lost Reason empty | H78: "Required Fields Missing — Lost Reason"; nothing is saved and the stage stays Qualified | I78: As expected | J78: Negative | K78: High | L78: Pass | N78: tests/opportunities/lifecycle.spec.ts
A79: OPP-078 | B79: UC-OPP-009 | C79: Mark Opportunity as Lost | D79: Mark as Lost from the Board | E79: Logged in as CRM Administrator; the board test opportunity (Qualified) from OPP-074 | F79: 1. Choose "Lost" in the test card's menu 2. Lost Reason "Timing", Remarks; click Continue 3. Click Go back, then repeat and click Confirm, then OK 4. Look at Qualified and Lost (Show) | G79: Reason "Timing"; remarks "Automated test - Board mark Lost" | H79: "Mark deal as Lost?" (Go back changes nothing); Confirm → "Opportunity Lost"; the card leaves Qualified and is listed under Lost; Qualified −1 and Lost +1; the opportunity is Lost with reason Timing | I79: As expected | J79: Functional | K79: High | L79: Pass | N79: tests/opportunities/lifecycle.spec.ts

Sheet Observations
A1: Obs ID | B1: Area | C1: Observation | D1: Expected / Question | E1: Suggested severity | F1: Related TC
A2: OBS-01 | B2: KPI cards | C2: The KPI tooltips quote stale counts: Total "Open (43) + Won (78) + Lost (4)" = 125 while the cards show 135; Pipeline Value and Avg Probability say 43 open deals while Open shows 47. | D2: Tooltip counts should be computed from the same data as the cards. | E2: Medium | F2: OPP-004
A3: OBS-02 | B3: Sort | C3: Sorting by Budget does not follow the USD amounts shown ("1M USD" before "7,738.14 USD" ascending). | D3: Sort by the amount converted to the base currency, as shown. | E3: Medium | F3: OPP-032
A4: OBS-03 | B4: Site visit | C4: A visit time picked as 11:00 is shown as 22:30 (saved as 17:00 UTC; browser on India time). | D4: The picked time should be shown back as picked; confirm which time zone visits use. | E4: High | F4: OPP-038
A5: OBS-04 | B5: Board | C5: Moves marked "(not from board)" can still be selected in a card's menu (choosing one does not change the stage). | D5: Disable those options so only allowed moves can be chosen. | E5: Low | F5: OPP-043
A6: OBS-05 | B6: Detail | C6: A link to an opportunity that does not exist opens the detail, shows "Loading…" and closes silently. | D6: Tell the user the opportunity was not found or is not accessible. | E6: Medium | F6: OPP-060
A7: OBS-06 | B7: Won | C7: A Won opportunity still offers "Mark Lost" in its detail, and Won cards on the Board still have a move menu. | D7: Question: may a Won deal still be marked Lost? If not, hide the action and refuse it in the backend. | E7: Question | F7: OPP-039, OPP-041
A8: OBS-07 | B8: Create | C8: There is no "Add Opportunity" form: opportunities are created only by converting a Qualified lead (Leads › Move to Opportunity). | D8: Confirm this is intended; UC-OPP-002 is tested through lead conversion. | E8: Info | F8: OPP-009 … OPP-018
A9: OBS-08 | B9: Edit | C9: There is no edit form for budget, probability, expected close or project; they change only through workflow actions. | D9: Confirm whether direct editing (UC-OPP-004) is in scope. | E9: Info | F9: OPP-020
A10: OBS-09 | B10: Delete | C10: There is no delete or deactivate action; the backend refuses DELETE; closing as Lost keeps the record. | D10: Confirm this is the intended policy for UC-OPP-011. | E10: Info | F10: OPP-054, OPP-055
A11: OBS-10 | B11: Convert | C11: Converting an already-converted lead again through the API answers 201 with the existing opportunity (no duplicate). | D11: Acceptable (idempotent); a 409 with a message would be clearer. | E11: Low | F11: OPP-052
