Workbook

Sheet Summary
A1: Reports & Analytics — Requirements Traceability Matrix
A3: Application | B3: ASQUARE CRM (QA) — https://qa-crm.asquareab.com
A4: Scope | B4: Reports & Analytics hub, Lead Reports, 9 report modules, Executive dashboard, cross-page consistency, Leads page (source data)
A5: Latest run | B5: 16-Oct-2026 06:53, full suite (599 tests, 4 workers) on QA
A6: Automation | B6: Playwright + TypeScript (Page Object Model); results from the run above
A7: Test case sources | B7: Lead_Reports_Test_Cases.xlsx, Reports_Analytics_Test_Scenarios.xlsx, page tests (one spec per hub card), core count / consistency suite
A9: Overall
A10: Requirements | B10: =COUNTA('Traceability Matrix'!$A$2:$A$99)
A11: Requirements fully passing | B11: =COUNTIF('Traceability Matrix'!$O$2:$O$99,"Pass")
A12: Requirements with failures | B12: =COUNTIF('Traceability Matrix'!$O$2:$O$99,"Fail")+COUNTIF('Traceability Matrix'!$O$2:$O$99,"Partly failing")
A13: Requirements skipped / not run | B13: =COUNTIF('Traceability Matrix'!$O$2:$O$99,"Skipped")+COUNTIF('Traceability Matrix'!$O$2:$O$99,"Not run")
A14: Requirement coverage (has test cases) | B14: =COUNTIF('Traceability Matrix'!$H$2:$H$99,">0")/B10
A15: Test cases | B15: =COUNTA('Test Case Mapping'!$A$2:$A$600)
A16: Automated test cases | B16: =COUNTIF('Test Case Mapping'!$G$2:$G$600,"Yes")
A17: Automation rate | B17: =B16/B15
A18: Passed | B18: =COUNTIF('Test Case Mapping'!$I$2:$I$600,"Pass")
A19: Failed | B19: =COUNTIF('Test Case Mapping'!$I$2:$I$600,"Fail")
A20: Skipped | B20: =COUNTIF('Test Case Mapping'!$I$2:$I$600,"Skipped")
A21: Pass rate (of executed) | B21: =IF(B18+B19=0,0,B18/(B18+B19))
A22: Known defects reproduced | B22: =COUNTIF(Defects!$G$2:$G$18,"Open (reproduced)")
A24: By page / area
A25: Page / Module | B25: Requirements | C25: Test cases | D25: Automated | E25: Passed | F25: Failed | G25: Skipped | H25: Pass rate | I25: Defects
A26: Reports & Analytics hub | B26: =COUNTIF('Traceability Matrix'!$C$2:$C$99,A26) | C26: =COUNTIF('Test Case Mapping'!$D$2:$D$600,A26) | D26: =COUNTIFS('Test Case Mapping'!$D$2:$D$600,A26,'Test Case Mapping'!$G$2:$G$600,"Yes") | E26: =COUNTIFS('Test Case Mapping'!$D$2:$D$600,A26,'Test Case Mapping'!$I$2:$I$600,"Pass") | F26: =COUNTIFS('Test Case Mapping'!$D$2:$D$600,A26,'Test Case Mapping'!$I$2:$I$600,"Fail") | G26: =COUNTIFS('Test Case Mapping'!$D$2:$D$600,A26,'Test Case Mapping'!$I$2:$I$600,"Skipped") | H26: =IF(E26+F26=0,"—",E26/(E26+F26)) | I26: —
A27: Lead Reports | B27: =COUNTIF('Traceability Matrix'!$C$2:$C$99,A27) | C27: =COUNTIF('Test Case Mapping'!$D$2:$D$600,A27) | D27: =COUNTIFS('Test Case Mapping'!$D$2:$D$600,A27,'Test Case Mapping'!$G$2:$G$600,"Yes") | E27: =COUNTIFS('Test Case Mapping'!$D$2:$D$600,A27,'Test Case Mapping'!$I$2:$I$600,"Pass") | F27: =COUNTIFS('Test Case Mapping'!$D$2:$D$600,A27,'Test Case Mapping'!$I$2:$I$600,"Fail") | G27: =COUNTIFS('Test Case Mapping'!$D$2:$D$600,A27,'Test Case Mapping'!$I$2:$I$600,"Skipped") | H27: =IF(E27+F27=0,"—",E27/(E27+F27)) | I27: DEF-01, DEF-12, DEF-13, DEF-14, DEF-15, DEF-16, DEF-17
A28: Sales Reports | B28: =COUNTIF('Traceability Matrix'!$C$2:$C$99,A28) | C28: =COUNTIF('Test Case Mapping'!$D$2:$D$600,A28) | D28: =COUNTIFS('Test Case Mapping'!$D$2:$D$600,A28,'Test Case Mapping'!$G$2:$G$600,"Yes") | E28: =COUNTIFS('Test Case Mapping'!$D$2:$D$600,A28,'Test Case Mapping'!$I$2:$I$600,"Pass") | F28: =COUNTIFS('Test Case Mapping'!$D$2:$D$600,A28,'Test Case Mapping'!$I$2:$I$600,"Fail") | G28: =COUNTIFS('Test Case Mapping'!$D$2:$D$600,A28,'Test Case Mapping'!$I$2:$I$600,"Skipped") | H28: =IF(E28+F28=0,"—",E28/(E28+F28)) | I28: DEF-01
A29: Inventory Reports | B29: =COUNTIF('Traceability Matrix'!$C$2:$C$99,A29) | C29: =COUNTIF('Test Case Mapping'!$D$2:$D$600,A29) | D29: =COUNTIFS('Test Case Mapping'!$D$2:$D$600,A29,'Test Case Mapping'!$G$2:$G$600,"Yes") | E29: =COUNTIFS('Test Case Mapping'!$D$2:$D$600,A29,'Test Case Mapping'!$I$2:$I$600,"Pass") | F29: =COUNTIFS('Test Case Mapping'!$D$2:$D$600,A29,'Test Case Mapping'!$I$2:$I$600,"Fail") | G29: =COUNTIFS('Test Case Mapping'!$D$2:$D$600,A29,'Test Case Mapping'!$I$2:$I$600,"Skipped") | H29: =IF(E29+F29=0,"—",E29/(E29+F29)) | I29: DEF-01
A30: Customer Reports | B30: =COUNTIF('Traceability Matrix'!$C$2:$C$99,A30) | C30: =COUNTIF('Test Case Mapping'!$D$2:$D$600,A30) | D30: =COUNTIFS('Test Case Mapping'!$D$2:$D$600,A30,'Test Case Mapping'!$G$2:$G$600,"Yes") | E30: =COUNTIFS('Test Case Mapping'!$D$2:$D$600,A30,'Test Case Mapping'!$I$2:$I$600,"Pass") | F30: =COUNTIFS('Test Case Mapping'!$D$2:$D$600,A30,'Test Case Mapping'!$I$2:$I$600,"Fail") | G30: =COUNTIFS('Test Case Mapping'!$D$2:$D$600,A30,'Test Case Mapping'!$I$2:$I$600,"Skipped") | H30: =IF(E30+F30=0,"—",E30/(E30+F30)) | I30: DEF-01, DEF-08
A31: Broker Reports | B31: =COUNTIF('Traceability Matrix'!$C$2:$C$99,A31) | C31: =COUNTIF('Test Case Mapping'!$D$2:$D$600,A31) | D31: =COUNTIFS('Test Case Mapping'!$D$2:$D$600,A31,'Test Case Mapping'!$G$2:$G$600,"Yes") | E31: =COUNTIFS('Test Case Mapping'!$D$2:$D$600,A31,'Test Case Mapping'!$I$2:$I$600,"Pass") | F31: =COUNTIFS('Test Case Mapping'!$D$2:$D$600,A31,'Test Case Mapping'!$I$2:$I$600,"Fail") | G31: =COUNTIFS('Test Case Mapping'!$D$2:$D$600,A31,'Test Case Mapping'!$I$2:$I$600,"Skipped") | H31: =IF(E31+F31=0,"—",E31/(E31+F31)) | I31: DEF-01
A32: Marketing Reports | B32: =COUNTIF('Traceability Matrix'!$C$2:$C$99,A32) | C32: =COUNTIF('Test Case Mapping'!$D$2:$D$600,A32) | D32: =COUNTIFS('Test Case Mapping'!$D$2:$D$600,A32,'Test Case Mapping'!$G$2:$G$600,"Yes") | E32: =COUNTIFS('Test Case Mapping'!$D$2:$D$600,A32,'Test Case Mapping'!$I$2:$I$600,"Pass") | F32: =COUNTIFS('Test Case Mapping'!$D$2:$D$600,A32,'Test Case Mapping'!$I$2:$I$600,"Fail") | G32: =COUNTIFS('Test Case Mapping'!$D$2:$D$600,A32,'Test Case Mapping'!$I$2:$I$600,"Skipped") | H32: =IF(E32+F32=0,"—",E32/(E32+F32)) | I32: DEF-01
A33: Reservation Reports | B33: =COUNTIF('Traceability Matrix'!$C$2:$C$99,A33) | C33: =COUNTIF('Test Case Mapping'!$D$2:$D$600,A33) | D33: =COUNTIFS('Test Case Mapping'!$D$2:$D$600,A33,'Test Case Mapping'!$G$2:$G$600,"Yes") | E33: =COUNTIFS('Test Case Mapping'!$D$2:$D$600,A33,'Test Case Mapping'!$I$2:$I$600,"Pass") | F33: =COUNTIFS('Test Case Mapping'!$D$2:$D$600,A33,'Test Case Mapping'!$I$2:$I$600,"Fail") | G33: =COUNTIFS('Test Case Mapping'!$D$2:$D$600,A33,'Test Case Mapping'!$I$2:$I$600,"Skipped") | H33: =IF(E33+F33=0,"—",E33/(E33+F33)) | I33: DEF-01
A34: SPA Reports | B34: =COUNTIF('Traceability Matrix'!$C$2:$C$99,A34) | C34: =COUNTIF('Test Case Mapping'!$D$2:$D$600,A34) | D34: =COUNTIFS('Test Case Mapping'!$D$2:$D$600,A34,'Test Case Mapping'!$G$2:$G$600,"Yes") | E34: =COUNTIFS('Test Case Mapping'!$D$2:$D$600,A34,'Test Case Mapping'!$I$2:$I$600,"Pass") | F34: =COUNTIFS('Test Case Mapping'!$D$2:$D$600,A34,'Test Case Mapping'!$I$2:$I$600,"Fail") | G34: =COUNTIFS('Test Case Mapping'!$D$2:$D$600,A34,'Test Case Mapping'!$I$2:$I$600,"Skipped") | H34: =IF(E34+F34=0,"—",E34/(E34+F34)) | I34: DEF-01
A35: Collection Reports | B35: =COUNTIF('Traceability Matrix'!$C$2:$C$99,A35) | C35: =COUNTIF('Test Case Mapping'!$D$2:$D$600,A35) | D35: =COUNTIFS('Test Case Mapping'!$D$2:$D$600,A35,'Test Case Mapping'!$G$2:$G$600,"Yes") | E35: =COUNTIFS('Test Case Mapping'!$D$2:$D$600,A35,'Test Case Mapping'!$I$2:$I$600,"Pass") | F35: =COUNTIFS('Test Case Mapping'!$D$2:$D$600,A35,'Test Case Mapping'!$I$2:$I$600,"Fail") | G35: =COUNTIFS('Test Case Mapping'!$D$2:$D$600,A35,'Test Case Mapping'!$I$2:$I$600,"Skipped") | H35: =IF(E35+F35=0,"—",E35/(E35+F35)) | I35: DEF-01, DEF-07
A36: Exception Reports | B36: =COUNTIF('Traceability Matrix'!$C$2:$C$99,A36) | C36: =COUNTIF('Test Case Mapping'!$D$2:$D$600,A36) | D36: =COUNTIFS('Test Case Mapping'!$D$2:$D$600,A36,'Test Case Mapping'!$G$2:$G$600,"Yes") | E36: =COUNTIFS('Test Case Mapping'!$D$2:$D$600,A36,'Test Case Mapping'!$I$2:$I$600,"Pass") | F36: =COUNTIFS('Test Case Mapping'!$D$2:$D$600,A36,'Test Case Mapping'!$I$2:$I$600,"Fail") | G36: =COUNTIFS('Test Case Mapping'!$D$2:$D$600,A36,'Test Case Mapping'!$I$2:$I$600,"Skipped") | H36: =IF(E36+F36=0,"—",E36/(E36+F36)) | I36: DEF-01
A37: Executive Reports (dashboard) | B37: =COUNTIF('Traceability Matrix'!$C$2:$C$99,A37) | C37: =COUNTIF('Test Case Mapping'!$D$2:$D$600,A37) | D37: =COUNTIFS('Test Case Mapping'!$D$2:$D$600,A37,'Test Case Mapping'!$G$2:$G$600,"Yes") | E37: =COUNTIFS('Test Case Mapping'!$D$2:$D$600,A37,'Test Case Mapping'!$I$2:$I$600,"Pass") | F37: =COUNTIFS('Test Case Mapping'!$D$2:$D$600,A37,'Test Case Mapping'!$I$2:$I$600,"Fail") | G37: =COUNTIFS('Test Case Mapping'!$D$2:$D$600,A37,'Test Case Mapping'!$I$2:$I$600,"Skipped") | H37: =IF(E37+F37=0,"—",E37/(E37+F37)) | I37: —
... A41: Business scenarios (all pages) | B41: =COUNTIF('Traceability Matrix'!$C$2:$C$99,A41) | C41: =COUNTIF('Test Case Mapping'!$D$2:$D$600,A41) | D41: =COUNTIFS('Test Case Mapping'!$D$2:$D$600,A41,'Test Case Mapping'!$G$2:$G$600,"Yes") | E41: =COUNTIFS('Test Case Mapping'!$D$2:$D$600,A41,'Test Case Mapping'!$I$2:$I$600,"Pass") | F41: =COUNTIFS('Test Case Mapping'!$D$2:$D$600,A41,'Test Case Mapping'!$I$2:$I$600,"Fail") | G41: =COUNTIFS('Test Case Mapping'!$D$2:$D$600,A41,'Test Case Mapping'!$I$2:$I$600,"Skipped") | H41: =IF(E41+F41=0,"—",E41/(E41+F41)) | I41: DEF-01, DEF-02, DEF-03, DEF-06, DEF-07, DEF-08, DEF-10, DEF-11
A42: Total | B42: =SUM(B26:B41) | C42: =SUM(C26:C41) | D42: =SUM(D26:D41) | E42: =SUM(E26:E41) | F42: =SUM(F26:F41) | G42: =SUM(G26:G41)

Sheet Traceability Matrix
A1: Requirement ID | B1: Area | C1: Page / Module | D1: Requirement | E1: Priority | F1: Test case sources | G1: Test case IDs | H1: Test cases | I1: Automated | J1: Passed | K1: Failed | L1: Skipped | M1: Not run | N1: Coverage | O1: Execution status | P1: Linked defects
A2: REQ-HUB-01 | B2: Reports & Analytics hub | C2: Reports & Analytics hub | D2: Executive Snapshot shows the 8 KPI values, valid, equal to the API and stable on reload | E2: High | F2: Core suite, Page tests (POM) | G2: HUB-01…HUB-03, RA-01…RA-03 | H2: =COUNTIF('Test Case Mapping'!$E$2:$E$600,A2) | I2: =COUNTIFS('Test Case Mapping'!$E$2:$E$600,A2,'Test Case Mapping'!$G$2:$G$600,"Yes") | J2: =COUNTIFS('Test Case Mapping'!$E$2:$E$600,A2,'Test Case Mapping'!$I$2:$I$600,"Pass") | K2: =COUNTIFS('Test Case Mapping'!$E$2:$E$600,A2,'Test Case Mapping'!$I$2:$I$600,"Fail") | L2: =COUNTIFS('Test Case Mapping'!$E$2:$E$600,A2,'Test Case Mapping'!$I$2:$I$600,"Skipped") | M2: =COUNTIFS('Test Case Mapping'!$E$2:$E$600,A2,'Test Case Mapping'!$I$2:$I$600,"Not run") | N2: =IF(H2=0,"Not covered",IF(I2=H2,"Automated",IF(I2=0,"Manual only","Partly manual"))) | O2: =IF(H2=0,"Not run",IF(K2>0,IF(J2>0,"Partly failing","Fail"),IF(J2>0,"Pass",IF(M2>0,"Not run","Skipped")))) | P2: —
A3: REQ-HUB-02 | B3: Reports & Analytics hub | C3: Reports & Analytics hub | D3: Module menu lists the 11 report cards with the right status, and each card opens its report | E3: High | F3: Core suite, Page tests (POM) | G3: HUB-04, HUB-05, RA-05 | H3: =COUNTIF('Test Case Mapping'!$E$2:$E$600,A3) | I3: =COUNTIFS('Test Case Mapping'!$E$2:$E$600,A3,'Test Case Mapping'!$G$2:$G$600,"Yes") | J3: =COUNTIFS('Test Case Mapping'!$E$2:$E$600,A3,'Test Case Mapping'!$I$2:$I$600,"Pass") | K3: =COUNTIFS('Test Case Mapping'!$E$2:$E$600,A3,'Test Case Mapping'!$I$2:$I$600,"Fail") | L3: =COUNTIFS('Test Case Mapping'!$E$2:$E$600,A3,'Test Case Mapping'!$I$2:$I$600,"Skipped") | M3: =COUNTIFS('Test Case Mapping'!$E$2:$E$600,A3,'Test Case Mapping'!$I$2:$I$600,"Not run") | N3: =IF(H3=0,"Not covered",IF(I3=H3,"Automated",IF(I3=0,"Manual only","Partly manual"))) | O3: =IF(H3=0,"Not run",IF(K3>0,IF(J3>0,"Partly failing","Fail"),IF(J3>0,"Pass",IF(M3>0,"Not run","Skipped")))) | P3: —
A4: REQ-HUB-03 | B4: Reports & Analytics hub | C4: Reports & Analytics hub | D4: Hub loads without JavaScript errors or failed API calls | E4: Medium | F4: Core suite, Page tests (POM) | G4: HUB-06, RA-04 | H4: =COUNTIF('Test Case Mapping'!$E$2:$E$600,A4) | I4: =COUNTIFS('Test Case Mapping'!$E$2:$E$600,A4,'Test Case Mapping'!$G$2:$G$600,"Yes") | J4: =COUNTIFS('Test Case Mapping'!$E$2:$E$600,A4,'Test Case Mapping'!$I$2:$I$600,"Pass") | K4: =COUNTIFS('Test Case Mapping'!$E$2:$E$600,A4,'Test Case Mapping'!$I$2:$I$600,"Fail") | L4: =COUNTIFS('Test Case Mapping'!$E$2:$E$600,A4,'Test Case Mapping'!$I$2:$I$600,"Skipped") | M4: =COUNTIFS('Test Case Mapping'!$E$2:$E$600,A4,'Test Case Mapping'!$I$2:$I$600,"Not run") | N4: =IF(H4=0,"Not covered",IF(I4=H4,"Automated",IF(I4=0,"Manual only","Partly manual"))) | O4: =IF(H4=0,"Not run",IF(K4>0,IF(J4>0,"Partly failing","Fail"),IF(J4>0,"Pass",IF(M4>0,"Not run","Skipped")))) | P4: —
A5: REQ-LR-01 | B5: Lead Reports | C5: Lead Reports | D5: Page access, navigation, breadcrumb, help text and the 5 tabs (including tab URLs, reload and Back) | E5: Medium | F5: Core suite, Lead Reports workbook, Page tests (POM) | G5: LDR-01, LDR-11, LR-001…LR-015, RA-MOD-01 | H5: =COUNTIF('Test Case Mapping'!$E$2:$E$600,A5) | I5: =COUNTIFS('Test Case Mapping'!$E$2:$E$600,A5,'Test Case Mapping'!$G$2:$G$600,"Yes") | J5: =COUNTIFS('Test Case Mapping'!$E$2:$E$600,A5,'Test Case Mapping'!$I$2:$I$600,"Pass") | K5: =COUNTIFS('Test Case Mapping'!$E$2:$E$600,A5,'Test Case Mapping'!$I$2:$I$600,"Fail") | L5: =COUNTIFS('Test Case Mapping'!$E$2:$E$600,A5,'Test Case Mapping'!$I$2:$I$600,"Skipped") | M5: =COUNTIFS('Test Case Mapping'!$E$2:$E$600,A5,'Test Case Mapping'!$I$2:$I$600,"Not run") | N5: =IF(H5=0,"Not covered",IF(I5=H5,"Automated",IF(I5=0,"Manual only","Partly manual"))) | O5: =IF(H5=0,"Not run",IF(K5>0,IF(J5>0,"Partly failing","Fail"),IF(J5>0,"Pass",IF(M5>0,"Not run","Skipped")))) | P5: DEF-12
A6: REQ-LR-02 | B6: Lead Reports | C6: Lead Reports | D6: Period dropdown and custom dates reload every figure for the chosen range | E6: High | F6: Lead Reports workbook, Page tests (POM) | G6: LDR-04…LDR-06, LR-016…LR-022 | H6: =COUNTIF('Test Case Mapping'!$E$2:$E$600,A6) | I6: =COUNTIFS('Test Case Mapping'!$E$2:$E$600,A6,'Test Case Mapping'!$G$2:$G$600,"Yes") | J6: =COUNTIFS('Test Case Mapping'!$E$2:$E$600,A6,'Test Case Mapping'!$I$2:$I$600,"Pass") | K6: =COUNTIFS('Test Case Mapping'!$E$2:$E$600,A6,'Test Case Mapping'!$I$2:$I$600,"Fail") | L6: =COUNTIFS('Test Case Mapping'!$E$2:$E$600,A6,'Test Case Mapping'!$I$2:$I$600,"Skipped") | M6: =COUNTIFS('Test Case Mapping'!$E$2:$E$600,A6,'Test Case Mapping'!$I$2:$I$600,"Not run") | N6: =IF(H6=0,"Not covered",IF(I6=H6,"Automated",IF(I6=0,"Manual only","Partly manual"))) | O6: =IF(H6=0,"Not run",IF(K6>0,IF(J6>0,"Partly failing","Fail"),IF(J6>0,"Pass",IF(M6>0,"Not run","Skipped")))) | P6: DEF-01
A7: REQ-LR-03 | B7: Lead Reports | C7: Lead Reports | D7: Each header filter (Project, Lead Source, Channel, Campaign, Broker, Salesperson, Prospect Type, Nationality) narrows the report; reset restores it | E7: High | F7: Lead Reports workbook, Page tests (POM) | G7: LDR-07, LDR-09, LR-023…LR-035 | H7: =COUNTIF('Test Case Mapping'!$E$2:$E$600,A7) | I7: =COUNTIFS('Test Case Mapping'!$E$2:$E$600,A7,'Test Case Mapping'!$G$2:$G$600,"Yes") | J7: =COUNTIFS('Test Case Mapping'!$E$2:$E$600,A7,'Test Case Mapping'!$I$2:$I$600,"Pass") | K7: =COUNTIFS('Test Case Mapping'!$E$2:$E$600,A7,'Test Case Mapping'!$I$2:$I$600,"Fail") | L7: =COUNTIFS('Test Case Mapping'!$E$2:$E$600,A7,'Test Case Mapping'!$I$2:$I$600,"Skipped") | M7: =COUNTIFS('Test Case Mapping'!$E$2:$E$600,A7,'Test Case Mapping'!$I$2:$I$600,"Not run") | N7: =IF(H7=0,"Not covered",IF(I7=H7,"Automated",IF(I7=0,"Manual only","Partly manual"))) | O7: =IF(H7=0,"Not run",IF(K7>0,IF(J7>0,"Partly failing","Fail"),IF(J7>0,"Pass",IF(M7>0,"Not run","Skipped")))) | P7: —
A8: REQ-LR-04 | B8: Lead Reports | C8: Lead Reports | D8: Filter combinations, clearing a filter, "All" values, empty / single-lead results and filter master data are handled correctly | E8: High | F8: Lead Reports workbook | G8: LR-147…LR-156 | H8: =COUNTIF('Test Case Mapping'!$E$2:$E$600,A8) | I8: =COUNTIFS('Test Case Mapping'!$E$2:$E$600,A8,'Test Case Mapping'!$G$2:$G$600,"Yes") | J8: =COUNTIFS('Test Case Mapping'!$E$2:$E$600,A8,'Test Case Mapping'!$I$2:$I$600,"Pass") | K8: =COUNTIFS('Test Case Mapping'!$E$2:$E$600,A8,'Test Case Mapping'!$I$2:$I$600,"Fail") | L8: =COUNTIFS('Test Case Mapping'!$E$2:$E$600,A8,'Test Case Mapping'!$I$2:$I$600,"Skipped") | M8: =COUNTIFS('Test Case Mapping'!$E$2:$E$600,A8,'Test Case Mapping'!$I$2:$I$600,"Not run") | N8: =IF(H8=0,"Not covered",IF(I8=H8,"Automated",IF(I8=0,"Manual only","Partly manual"))) | O8: =IF(H8=0,"Not run",IF(K8>0,IF(J8>0,"Partly failing","Fail"),IF(J8>0,"Pass",IF(M8>0,"Not run","Skipped")))) | P8: DEF-17
A9: REQ-LR-05 | B9: Lead Reports | C9: Lead Reports | D9: With each filter applied, every count on every tab is correct (cards, funnel, lists, tables, aging, qualification, scorecard) | E9: High | F9: Lead Reports workbook | G9: LR-157…LR-166 | H9: =COUNTIF('Test Case Mapping'!$E$2:$E$600,A9) | I9: =COUNTIFS('Test Case Mapping'!$E$2:$E$600,A9,'Test Case Mapping'!$G$2:$G$600,"Yes") | J9: =COUNTIFS('Test Case Mapping'!$E$2:$E$600,A9,'Test Case Mapping'!$I$2:$I$600,"Pass") | K9: =COUNTIFS('Test Case Mapping'!$E$2:$E$600,A9,'Test Case Mapping'!$I$2:$I$600,"Fail") | L9: =COUNTIFS('Test Case Mapping'!$E$2:$E$600,A9,'Test Case Mapping'!$I$2:$I$600,"Skipped") | M9: =COUNTIFS('Test Case Mapping'!$E$2:$E$600,A9,'Test Case Mapping'!$I$2:$I$600,"Not run") | N9: =IF(H9=0,"Not covered",IF(I9=H9,"Automated",IF(I9=0,"Manual only","Partly manual"))) | O9: =IF(H9=0,"Not run",IF(K9>0,IF(J9>0,"Partly failing","Fail"),IF(J9>0,"Pass",IF(M9>0,"Not run","Skipped")))) | P9: DEF-17
A10: REQ-LR-06 | B10: Lead Reports | C10: Lead Reports | D10: Views All / You and your team / Mine show the right scope for the user's role | E10: High | F10: Lead Reports workbook, Page tests (POM) | G10: LDR-08, LR-036…LR-041 | H10: =COUNTIF('Test Case Mapping'!$E$2:$E$600,A10) | I10: =COUNTIFS('Test Case Mapping'!$E$2:$E$600,A10,'Test Case Mapping'!$G$2:$G$600,"Yes") | J10: =COUNTIFS('Test Case Mapping'!$E$2:$E$600,A10,'Test Case Mapping'!$I$2:$I$600,"Pass") | K10: =COUNTIFS('Test Case Mapping'!$E$2:$E$600,A10,'Test Case Mapping'!$I$2:$I$600,"Fail") | L10: =COUNTIFS('Test Case Mapping'!$E$2:$E$600,A10,'Test Case Mapping'!$I$2:$I$600,"Skipped") | M10: =COUNTIFS('Test Case Mapping'!$E$2:$E$600,A10,'Test Case Mapping'!$I$2:$I$600,"Not run") | N10: =IF(H10=0,"Not covered",IF(I10=H10,"Automated",IF(I10=0,"Manual only","Partly manual"))) | O10: =IF(H10=0,"Not run",IF(K10>0,IF(J10>0,"Partly failing","Fail"),IF(J10>0,"Pass",IF(M10>0,"Not run","Skipped")))) | P10: —
A11: REQ-LR-07 | B11: Lead Reports | C11: Lead Reports | D11: Overview KPI cards (counts, rates, Won Value, time to first contact, Open Leads Now) are correct | E11: High | F11: Core suite, Lead Reports workbook, Page tests (POM) | G11: LDR-02, LDR-03, LR-042…LR-053, RM-01 | H11: =COUNTIF('Test Case Mapping'!$E$2:$E$600,A11) | I11: =COUNTIFS('Test Case Mapping'!$E$2:$E$600,A11,'Test Case Mapping'!$G$2:$G$600,"Yes") | J11: =COUNTIFS('Test Case Mapping'!$E$2:$E$600,A11,'Test Case Mapping'!$I$2:$I$600,"Pass") | K11: =COUNTIFS('Test Case Mapping'!$E$2:$E$600,A11,'Test Case Mapping'!$I$2:$I$600,"Fail") | L11: =COUNTIFS('Test Case Mapping'!$E$2:$E$600,A11,'Test Case Mapping'!$I$2:$I$600,"Skipped") | M11: =COUNTIFS('Test Case Mapping'!$E$2:$E$600,A11,'Test Case Mapping'!$I$2:$I$600,"Not run") | N11: =IF(H11=0,"Not covered",IF(I11=H11,"Automated",IF(I11=0,"Manual only","Partly manual"))) | O11: =IF(H11=0,"Not run",IF(K11>0,IF(J11>0,"Partly failing","Fail"),IF(J11>0,"Pass",IF(M11>0,"Not run","Skipped")))) | P11: —
A12: REQ-LR-08 | B12: Lead Reports | C12: Lead Reports | D12: Lead Funnel, Data Completeness and 12-Month Trend are correct and consistent with the cards | E12: High | F12: Lead Reports workbook, Page tests (POM) | G12: LDR-12…LDR-16, LR-054…LR-067 | H12: =COUNTIF('Test Case Mapping'!$E$2:$E$600,A12) | I12: =COUNTIFS('Test Case Mapping'!$E$2:$E$600,A12,'Test Case Mapping'!$G$2:$G$600,"Yes") | J12: =COUNTIFS('Test Case Mapping'!$E$2:$E$600,A12,'Test Case Mapping'!$I$2:$I$600,"Pass") | K12: =COUNTIFS('Test Case Mapping'!$E$2:$E$600,A12,'Test Case Mapping'!$I$2:$I$600,"Fail") | L12: =COUNTIFS('Test Case Mapping'!$E$2:$E$600,A12,'Test Case Mapping'!$I$2:$I$600,"Skipped") | M12: =COUNTIFS('Test Case Mapping'!$E$2:$E$600,A12,'Test Case Mapping'!$I$2:$I$600,"Not run") | N12: =IF(H12=0,"Not covered",IF(I12=H12,"Automated",IF(I12=0,"Manual only","Partly manual"))) | O12: =IF(H12=0,"Not run",IF(K12>0,IF(J12>0,"Partly failing","Fail"),IF(J12>0,"Pass",IF(M12>0,"Not run","Skipped")))) | P12: —
A13: REQ-LR-09 | B13: Lead Reports | C13: Lead Reports | D13: Every count link opens a drill-down list with exactly that many leads, matching its export and its bucket rules | E13: High | F13: Lead Reports workbook, Lead Reports workbook (Drill-down Verification) | G13: LR-068…LR-079, LR-145, LR-146, LR-DDV-01…LR-DDV-13 | H13: =COUNTIF('Test Case Mapping'!$E$2:$E$600,A13) | I13: =COUNTIFS('Test Case Mapping'!$E$2:$E$600,A13,'Test Case Mapping'!$G$2:$G$600,"Yes") | J13: =COUNTIFS('Test Case Mapping'!$E$2:$E$600,A13,'Test Case Mapping'!$I$2:$I$600,"Pass") | K13: =COUNTIFS('Test Case Mapping'!$E$2:$E$600,A13,'Test Case Mapping'!$I$2:$I$600,"Fail") | L13: =COUNTIFS('Test Case Mapping'!$E$2:$E$600,A13,'Test Case Mapping'!$I$2:$I$600,"Skipped") | M13: =COUNTIFS('Test Case Mapping'!$E$2:$E$600,A13,'Test Case Mapping'!$I$2:$I$600,"Not run") | N13: =IF(H13=0,"Not covered",IF(I13=H13,"Automated",IF(I13=0,"Manual only","Partly manual"))) | O13: =IF(H13=0,"Not run",IF(K13>0,IF(J13>0,"Partly failing","Fail"),IF(J13>0,"Pass",IF(M13>0,"Not run","Skipped")))) | P13: DEF-12
... A99: REQ-SC-17 | B99: Business scenarios (workbook) | C99: Business scenarios (all pages) | D99: End-to-End Scenarios (scenarios from Reports_Analytics_Test_Scenarios.xlsx) | E99: Medium | F99: Scenarios workbook | G99: RA-127…RA-133 | H99: =COUNTIF('Test Case Mapping'!$E$2:$E$600,A99) | I99: =COUNTIFS('Test Case Mapping'!$E$2:$E$600,A99,'Test Case Mapping'!$G$2:$G$600,"Yes") | J99: =COUNTIFS('Test Case Mapping'!$E$2:$E$600,A99,'Test Case Mapping'!$I$2:$I$600,"Pass") | K99: =COUNTIFS('Test Case Mapping'!$E$2:$E$600,A99,'Test Case Mapping'!$I$2:$I$600,"Fail") | L99: =COUNTIFS('Test Case Mapping'!$E$2:$E$600,A99,'Test Case Mapping'!$I$2:$I$600,"Skipped") | M99: =COUNTIFS('Test Case Mapping'!$E$2:$E$600,A99,'Test Case Mapping'!$I$2:$I$600,"Not run") | N99: =IF(H99=0,"Not covered",IF(I99=H99,"Automated",IF(I99=0,"Manual only","Partly manual"))) | O99: =IF(H99=0,"Not run",IF(K99>0,IF(J99>0,"Partly failing","Fail"),IF(J99>0,"Pass",IF(M99>0,"Not run","Skipped")))) | P99: —

Sheet Test Case Mapping
A1: Test Case ID | B1: Test Case | C1: Source | D1: Page / Module | E1: Requirement ID | F1: Priority | G1: Automated | H1: Spec file | I1: Latest Result | J1: Defect ID | K1: Failure / skip detail
A2: X-01 | B2: Active leads is the same on every page | C2: Core suite | D2: Hub, dashboard and report modules | E2: REQ-X-01 | G2: Yes | H2: tests/consistency.spec.ts | I2: Pass
A3: X-02 | B3: Open opportunities is the same on every page | C3: Core suite | D3: Hub, dashboard and report modules | E3: REQ-X-01 | G3: Yes | H3: tests/consistency.spec.ts | I3: Fail | J3: DEF-02 | K3: Error: Open opportunities differs:
A4: X-03 | B4: Pipeline value is the same on every page | C4: Core suite | D4: Hub, dashboard and report modules | E4: REQ-X-01 | G4: Yes | H4: tests/consistency.spec.ts | I4: Fail | J4: DEF-03 | K4: Error: Pipeline value differs:
A5: X-04 | B5: Weighted pipeline is the same on every page | C5: Core suite | D5: Hub, dashboard and report modules | E5: REQ-X-01 | G5: Yes | H5: tests/consistency.spec.ts | I5: Fail | J5: DEF-03 | K5: Error: Weighted pipeline differs:
A6: X-05 | B6: Units available is the same on every page | C6: Core suite | D6: Hub, dashboard and report modules | E6: REQ-X-01 | G6: Yes | H6: tests/consistency.spec.ts | I6: Pass
A7: X-06 | B7: Units reserved is the same on every page | C7: Core suite | D7: Hub, dashboard and report modules | E7: REQ-X-01 | G7: Yes | H7: tests/consistency.spec.ts | I7: Pass | J7: DEF-04
A8: X-07 | B8: Units sold is the same on every page | C8: Core suite | D8: Hub, dashboard and report modules | E8: REQ-X-01 | G8: Yes | H8: tests/consistency.spec.ts | I8: Pass | J8: DEF-04
A9: X-08 | B9: SPA value signed this month is the same on every page | C9: Core suite | D9: Hub, dashboard and report modules | E9: REQ-X-01 | G9: Yes | H9: tests/consistency.spec.ts | I9: Pass
A10: X-09 | B10: SPAs signed this month is the same on every page | C10: Core suite | D10: Hub, dashboard and report modules | E10: REQ-X-01 | G10: Yes | H10: tests/consistency.spec.ts | I10: Pass
A11: X-10 | B11: Won opportunities this month is the same on every page | C11: Core suite | D11: Hub, dashboard and report modules | E11: REQ-X-01 | G11: Yes | H11: tests/consistency.spec.ts | I11: Fail | J11: DEF-05 | K11: Error: Won opportunities this month differs:
A12: X-11 | B12: Collections received is the same on every page | C12: Core suite | D12: Hub, dashboard and report modules | E12: REQ-X-01 | G12: Yes | H12: tests/consistency.spec.ts | I12: Pass
A13: X-12 | B13: Outstanding amount is the same on every page | C13: Core suite | D13: Hub, dashboard and report modules | E13: REQ-X-01 | G13: Yes | H13: tests/consistency.spec.ts | I13: Pass
A14: X-13 | B14: Reservations past expiry is the same on every page | C14: Core suite | D14: Hub, dashboard and report modules | E14: REQ-X-01 | G14: Yes | H14: tests/consistency.spec.ts | I14: Pass
A15: X-14 | B15: Active reservations is the same on every page | C15: Core suite | D15: Hub, dashboard and report modules | E15: REQ-X-01 | G15: Yes | H15: tests/consistency.spec.ts | I15: Pass
A16: X-15 | B16: Reservations expiring in 7 days is the same on every page | C16: Core suite | D16: Hub, dashboard and report modules | E16: REQ-X-01 | G16: Yes | H16: tests/consistency.spec.ts | I16: Pass
A17: X-16 | B17: Won value is the same on every page | C17: Core suite | D17: Hub, dashboard and report modules | E17: REQ-X-01 | G17: Yes | H17: tests/consistency.spec.ts | I17: Pass
A18: M-01 | B18: Hub: Available + Reserved + Sold = Inventory total units | C18: Core suite | D18: Hub, dashboard and report modules | E18: REQ-X-01 | G18: Yes | H18: tests/consistency.spec.ts | I18: Pass
A19: M-02 | B19: Inventory: Available + Reserved + Sold (+Other) = Total; Sold % correct; project table sums | C19: Core suite | D19: Inventory Reports | E19: REQ-INV-06 | G19: Yes | H19: tests/consistency.spec.ts | I19: Pass
A20: M-03 | B20: Collections: Scheduled − Received = Outstanding; rates add up | C20: Core suite | D20: Collection Reports | E20: REQ-COL-06 | G20: Yes | H20: tests/consistency.spec.ts | I20: Fail | J20: DEF-07 | K20: Error: Collection rate = Received / Scheduled
A21: M-04 | B21: Reservations: Conversion rate = Converted / Reservations | C21: Core suite | D21: Reservation Reports | E21: REQ-RES-06 | G21: Yes | H21: tests/consistency.spec.ts | I21: Pass
A22: M-05 | B22: SPA: Average SPA value = Signed value / SPAs signed | C22: Core suite | D22: SPA Reports | E22: REQ-SPA-06 | G22: Yes | H22: tests/consistency.spec.ts | I22: Pass
A23: M-06 | B23: Marketing: Cost per lead = Budget / Campaign leads | C23: Core suite | D23: Marketing Reports | E23: REQ-MKT-06 | G23: Yes | H23: tests/consistency.spec.ts | I23: Pass
A24: M-07 | B24: Exceptions: Open exceptions = sum of the summary table "Open" column | C24: Core suite | D24: Exception Reports | E24: REQ-EXC-06 | G24: Yes | H24: tests/consistency.spec.ts | I24: Pass
A25: M-08 | B25: Sales: stage table total = Open opportunities and Pipeline value | C25: Core suite | D25: Sales Reports | E25: REQ-SAL-06 | G25: Yes | H25: tests/consistency.spec.ts | I25: Pass
A26: DB-RA-01 | B26: Active Leads: UI = DB | C26: Database checks | D26: All report pages | E26: REQ-X-02 | G26: Yes | H26: tests/db.spec.ts | I26: Skipped | K26: Database tests off (SKIP_DB_TESTS=true) or not configured — see .env
A27: DB-RA-02 | B27: Open Opportunities: UI = DB | C27: Database checks | D27: All report pages | E27: REQ-X-02 | G27: Yes | H27: tests/db.spec.ts | I27: Skipped | K27: Database tests off (SKIP_DB_TESTS=true) or not configured — see .env
A28: DB-RA-03 | B28: Units Reserved: UI = DB | C28: Database checks | D28: All report pages | E28: REQ-X-02 | G28: Yes | H28: tests/db.spec.ts | I28: Skipped | K28: Database tests off (SKIP_DB_TESTS=true) or not configured — see .env
A29: DB-RA-04 | B29: Units Available: UI = DB | C29: Database checks | D29: All report pages | E29: REQ-X-02 | G29: Yes | H29: tests/db.spec.ts | I29: Skipped | K29: Database tests off (SKIP_DB_TESTS=true) or not configured — see .env
A30: DB-RA-05 | B30: Pipeline Value (USD): UI = DB | C30: Database checks | D30: All report pages | E30: REQ-X-02 | G30: Yes | H30: tests/db.spec.ts | I30: Skipped | K30: Database tests off (SKIP_DB_TESTS=true) or not configured — see .env
A31: DB-RA-06 | B31: SPA Value Signed (This Month): UI = DB | C31: Database checks | D31: All report pages | E31: REQ-X-02 | G31: Yes | H31: tests/db.spec.ts | I31: Skipped | K31: Database tests off (SKIP_DB_TESTS=true) or not configured — see .env
A32: DB-RA-07 | B32: Units Sold: UI = DB | C32: Database checks | D32: All report pages | E32: REQ-X-02 | G32: Yes | H32: tests/db.spec.ts | I32: Skipped | K32: Database tests off (SKIP_DB_TESTS=true) or not configured — see .env
A33: DB-RA-08 | B33: Weighted Pipeline (USD): UI = DB | C33: Database checks | D33: All report pages | E33: REQ-X-02 | G33: Yes | H33: tests/db.spec.ts | I33: Skipped | K33: Database tests off (SKIP_DB_TESTS=true) or not configured — see .env
A34: DB-L-01 | B34: Total Leads: UI = DB | C34: Database checks | D34: All report pages | E34: REQ-X-02 | G34: Yes | H34: tests/db.spec.ts | I34: Skipped | K34: Database tests off (SKIP_DB_TESTS=true) or not configured — see .env
A35: DB-L-02 | B35: Assigned: UI = DB | C35: Database checks | D35: All report pages | E35: REQ-X-02 | G35: Yes | H35: tests/db.spec.ts | I35: Skipped | K35: Database tests off (SKIP_DB_TESTS=true) or not configured — see .env
A36: DB-L-03 | B36: Unassigned tab: UI = DB | C36: Database checks | D36: All report pages | E36: REQ-X-02 | G36: Yes | H36: tests/db.spec.ts | I36: Skipped | K36: Database tests off (SKIP_DB_TESTS=true) or not configured — see .env
A37: DB-L-04 | B37: Qualified: UI = DB | C37: Database checks | D37: All report pages | E37: REQ-X-02 | G37: Yes | H37: tests/db.spec.ts | I37: Skipped | K37: Database tests off (SKIP_DB_TESTS=true) or not configured — see .env
... A43: DB-L-10 | B43: every status count in the Leads filter = DB GROUP BY status | C43: Database checks | D43: All report pages | E43: REQ-X-02 | G43: Yes | H43: tests/db.spec.ts | I43: Skipped | K43: Database tests off (SKIP_DB_TESTS=true) or not configured — see .env
A44: LR-103 | B44: 4 aging KPI cards | C44: Lead Reports workbook | D44: Lead Reports | E44: REQ-LR-11 | F44: High | G44: Yes | H44: tests/lead-reports/aging.spec.ts | I44: Pass
A45: LR-104 | B45: "Open Leads" count opens its leads | C45: Lead Reports workbook | D45: Lead Reports | E45: REQ-LR-11 | F45: High | G45: Yes | H45: tests/lead-reports/aging.spec.ts | I45: Pass
A46: LR-105 | B46: "Idle Over 30 Days" count opens its leads | C46: Lead Reports workbook | D46: Lead Reports | E46: REQ-LR-11 | F46: High | G46: Yes | H46: tests/lead-reports/aging.spec.ts | I46: Pass
A47: LR-106 | B47: "Never Contacted" count opens its leads | C47: Lead Reports workbook | D47: Lead Reports | E47: REQ-LR-11 | F47: High | G47: Yes | H47: tests/lead-reports/aging.spec.ts | I47: Pass
A48: LR-107 | B48: Overdue Follow-ups | C48: Lead Reports workbook | D48: Lead Reports | E48: REQ-LR-11 | F48: Low | G48: Yes | H48: tests/lead-reports/aging.spec.ts | I48: Pass
A49: LR-108 | B49: Aging ignores the period | C49: Lead Reports workbook | D49: Lead Reports | E49: REQ-LR-11 | F49: Medium | G49: Yes | H49: tests/lead-reports/aging.spec.ts | I49: Pass
A50: LR-109 | B50: Idle Time buckets add up to Open Leads | C50: Lead Reports workbook | D50: Lead Reports | E50: REQ-LR-11 | F50: High | G50: Yes | H50: tests/lead-reports/aging.spec.ts | I50: Pass
A51: LR-110 | B51: Lead Age buckets add up to Open Leads | C51: Lead Reports workbook | D51: Lead Reports | E51: REQ-LR-11 | F51: High | G51: Yes | H51: tests/lead-reports/aging.spec.ts | I51: Pass
A52: LR-111 | B52: Salesperson table adds up | C52: Lead Reports workbook | D52: Lead Reports | E52: REQ-LR-11 | F52: High | G52: Yes | H52: tests/lead-reports/aging.spec.ts | I52: Pass
A53: LR-112 | B53: Open and Never Contacted counts open their leads | C53: Lead Reports workbook | D53: Lead Reports | E53: REQ-LR-11 | F53: Medium | G53: Yes | H53: tests/lead-reports/aging.spec.ts | I53: Pass
A54: LR-113 | B54: Aging export | C54: Lead Reports workbook | D54: Lead Reports | E54: REQ-LR-11 | F54: Medium | G54: Yes | H54: tests/lead-reports/aging.spec.ts | I54: Pass
A55: LR-114 | B55: Status table adds up | C55: Lead Reports workbook | D55: Lead Reports | E55: REQ-LR-11 | F55: Medium | G55: Yes | H55: tests/lead-reports/aging.spec.ts | I55: Pass
... A57: LR-116 | B57: Lead link opens the lead | C57: Lead Reports workbook | D57: Lead Reports | E57: REQ-LR-11 | F57: Medium | G57: Yes | H57: tests/lead-reports/aging.spec.ts | I57: Pass
A58: LR-MAP-00 | B58: Every Clickable Map row has a check | C58: Lead Reports workbook (Clickable Map) | D58: Lead Reports | E58: REQ-LR-15 | G58: Yes | H58: tests/lead-reports/clickable-map.spec.ts | I58: Pass
A59: LR-MAP-01 | B59: All › REPORTS & ANALYTICS breadcrumb — clickable: Yes | C59: Lead Reports workbook (Clickable Map) | D59: Lead Reports | E59: REQ-LR-15 | G59: Yes | H59: tests/lead-reports/clickable-map.spec.ts | I59: Pass
A60: LR-MAP-02 | B60: All › 9 filter dropdowns (Period, Project, Lead Source, Capture Channel, Campaign, Broker, Salesperson, Prospect Type, Nationality) — clickable: Yes | C60: Lead Reports workbook (Clickable Map) | D60: Lead Reports | E60: REQ-LR-15 | G60: Yes | H60: tests/lead-reports/clickable-map.spec.ts | I60: Pass
A61: LR-MAP-03 | B61: All › Custom dates From / To — clickable: Yes | C61: Lead Reports workbook (Clickable Map) | D61: Lead Reports | E61: REQ-LR-15 | G61: Yes | H61: tests/lead-reports/clickable-map.spec.ts | I61: Pass
A62: LR-MAP-04 | B62: All › View: All / You and your team / Mine — clickable: Yes | C62: Lead Reports workbook (Clickable Map) | D62: Lead Reports | E62: REQ-LR-15 | G62: Yes | H62: tests/lead-reports/clickable-map.spec.ts | I62: Pass
A63: LR-MAP-05 | B63: All › Reset filters — clickable: Yes (disabled until a change) | C63: Lead Reports workbook (Clickable Map) | D63: Lead Reports | E63: REQ-LR-15 | G63: Yes | H63: tests/lead-reports/clickable-map.spec.ts | I63: Pass
A64: LR-MAP-06 | B64: All › How these numbers are calculated — clickable: Yes | C64: Lead Reports workbook (Clickable Map) | D64: Lead Reports | E64: REQ-LR-15 | G64: Yes | H64: tests/lead-reports/clickable-map.spec.ts | I64: Pass
A65: LR-MAP-07 | B65: All › 5 tabs — clickable: Yes | C65: Lead Reports workbook (Clickable Map) | D65: Lead Reports | E65: REQ-LR-15 | G65: Yes | H65: tests/lead-reports/clickable-map.spec.ts | I65: Pass
A66: LR-MAP-08 | B66: Overview & Funnel › Leads Captured value — clickable: Yes | C66: Lead Reports workbook (Clickable Map) | D66: Lead Reports | E66: REQ-LR-15 | G66: Yes | H66: tests/lead-reports/clickable-map.spec.ts | I66: Pass
A67: LR-MAP-09 | B67: Overview & Funnel › SPA Signed value — clickable: Yes | C67: Lead Reports workbook (Clickable Map) | D67: Lead Reports | E67: REQ-LR-15 | G67: Yes | H67: tests/lead-reports/clickable-map.spec.ts | I67: Pass
A68: LR-MAP-10 | B68: Overview & Funnel › Open Leads Now value / idle / never contacted — clickable: Yes (3 links) | C68: Lead Reports workbook (Clickable Map) | D68: Lead Reports | E68: REQ-LR-15 | G68: Yes | H68: tests/lead-reports/clickable-map.spec.ts | I68: Pass
A69: LR-MAP-11 | B69: Overview & Funnel › Contact Rate, Qualification Rate, Opportunity Conversion, Won Value, Avg Time to First Contact — clickable: No | C69: Lead Reports workbook (Clickable Map) | D69: Lead Reports | E69: REQ-LR-15 | G69: Yes | H69: tests/lead-reports/clickable-map.spec.ts | I69: Pass
... A91: LR-COV-01 | B91: Every test case in Lead_Reports_Test_Cases.xlsx is automated | C91: Lead Reports workbook (coverage check) | D91: Lead Reports | E91: REQ-LR-16 | G91: Yes | H91: tests/lead-reports/coverage.spec.ts | I91: Pass
A92: LR-139 | B92: Open Leads Now equals hub Active Leads | C92: Lead Reports workbook | D92: Lead Reports | E92: REQ-LR-14 | F92: High | G92: Yes | H92: tests/lead-reports/cross-page.spec.ts | I92: Pass
A93: LR-140 | B93: SPA Signed and Won Value match SPA and Sales Reports | C93: Lead Reports workbook | D93: Lead Reports | E93: REQ-LR-14 | F93: High | G93: Yes | H93: tests/lead-reports/cross-page.spec.ts | I93: Pass
A94: LR-141 | B94: Usable on tablet and phone | C94: Lead Reports workbook | D94: Lead Reports | E94: REQ-LR-14 | F94: Medium | G94: Yes | H94: tests/lead-reports/cross-page.spec.ts | I94: Fail | J94: DEF-13 | K94: Error: phone overview: no page-wide horizontal scroll ("Lead Funnel" 42px too wide, "Data Completeness" 42px too wide)
A95: LR-142 | B95: Keyboard access to counts and tabs | C95: Lead Reports workbook | D95: Lead Reports | E95: REQ-LR-14 | F95: Medium | G95: Yes | H95: tests/lead-reports/cross-page.spec.ts | I95: Pass
A96: LR-143 | B96: Report and drill-downs load quickly | C96: Lead Reports workbook | D96: Lead Reports | E96: REQ-LR-14 | F96: Medium | G96: Yes | H96: tests/lead-reports/cross-page.spec.ts | I96: Pass
A97: LR-144 | B97: API failure shows a message | C97: Lead Reports workbook | D97: Lead Reports | E97: REQ-LR-14 | F97: Medium | G97: Yes | H97: tests/lead-reports/cross-page.spec.ts | I97: Pass
A98: LR-068 | B98: Drill-down list layout | C98: Lead Reports workbook | D98: Lead Reports | E98: REQ-LR-09 | F98: High | G98: Yes | H98: tests/lead-reports/drill-down.spec.ts | I98: Pass
A99: LR-069 | B99: Rows listed = the number clicked | C99: Lead Reports workbook | D99: Lead Reports | E99: REQ-LR-09 | F99: High | G99: Yes | H99: tests/lead-reports/drill-down.spec.ts | I99: Pass
A100: LR-070 | B100: Lists over 500 leads say they are truncated | C100: Lead Reports workbook | D100: Lead Reports | E100: REQ-LR-09 | F100: Medium | G100: Yes | H100: tests/lead-reports/drill-down.spec.ts | I100: Pass
A101: LR-071 | B101: Export downloads the listed leads | C101: Lead Reports workbook | D101: Lead Reports | E101: REQ-LR-09 | F101: High | G101: Yes | H101: tests/lead-reports/drill-down.spec.ts | I101: Pass
A102: LR-072 | B102: Export of a truncated list contains every lead | C102: Lead Reports workbook | D102: Lead Reports | E102: REQ-LR-09 | F102: High | G102: Yes | H102: tests/lead-reports/drill-down.spec.ts | I102: Pass
A103: LR-073 | B103: Close removes the list | C103: Lead Reports workbook | D103: Lead Reports | E103: REQ-LR-09 | F103: Medium | G103: Yes | H103: tests/lead-reports/drill-down.spec.ts | I103: Pass
A104: LR-074 | B104: Escape closes the list | C104: Lead Reports workbook | D104: Lead Reports | E104: REQ-LR-09 | F104: Low | G104: Yes | H104: tests/lead-reports/drill-down.spec.ts | I104: Fail | J104: DEF-12 | K104: Error: List closed by Esc
A105: LR-075 | B105: Opening another count replaces the list | C105: Lead Reports workbook | D105: Lead Reports | E105: REQ-LR-09 | F105: Medium | G105: Yes | H105: tests/lead-reports/drill-down.spec.ts | I105: Pass
A106: LR-076 | B106: Switching tab closes the list | C106: Lead Reports workbook | D106: Lead Reports | E106: REQ-LR-09 | F106: Medium | G106: Yes | H106: tests/lead-reports/drill-down.spec.ts | I106: Pass
A107: LR-077 | B107: Lead number opens the lead | C107: Lead Reports workbook | D107: Lead Reports | E107: REQ-LR-09 | F107: High | G107: Yes | H107: tests/lead-reports/drill-down.spec.ts | I107: Pass
A108: LR-078 | B108: Rows match the bucket | C108: Lead Reports workbook | D108: Lead Reports | E108: REQ-LR-09 | F108: High | G108: Yes | H108: tests/lead-reports/drill-down.spec.ts | I108: Pass
A109: LR-079 | B109: "as of today" lists ignore the period | C109: Lead Reports workbook | D109: Lead Reports | E109: REQ-LR-09 | F109: Medium | G109: Yes | H109: tests/lead-reports/drill-down.spec.ts | I109: Pass
A110: LR-145 | B110: Zero counts are not links | C110: Lead Reports workbook | D110: Lead Reports | E110: REQ-LR-09 | F110: Low | G110: Yes | H110: tests/lead-reports/drill-down.spec.ts | I110: Pass
A111: LR-146 | B111: Every count link agrees with its list and export | C111: Lead Reports workbook | D111: Lead Reports | E111: REQ-LR-09 | F111: High | G111: Yes | H111: tests/lead-reports/drill-down.spec.ts | I111: Pass
A112: LR-DDV-01 | B112: Drill-down verification: Overview & Funnel (KPI cards and funnel) | C112: Lead Reports workbook (Drill-down Verification) | D112: Lead Reports | E112: REQ-LR-09 | G112: Yes | H112: tests/lead-reports/drill-verification.spec.ts | I112: Pass
A113: LR-DDV-02 | B113: Drill-down verification: Source & Channel grouped by Lead Source (every count) | C113: Lead Reports workbook (Drill-down Verification) | D113: Lead Reports | E113: REQ-LR-09 | G113: Yes | H113: tests/lead-reports/drill-verification.spec.ts | I113: Pass
A114: LR-DDV-03 | B114: Drill-down verification: Source & Channel grouped by Capture Channel ("Leads" of every row) | C114: Lead Reports workbook (Drill-down Verification) | D114: Lead Reports | E114: REQ-LR-09 | G114: Yes | H114: tests/lead-reports/drill-verification.spec.ts | I114: Pass
A115: LR-DDV-04 | B115: Drill-down verification: Source & Channel grouped by Campaign ("Leads" of every row) | C115: Lead Reports workbook (Drill-down Verification) | D115: Lead Reports | E115: REQ-LR-09 | G115: Yes | H115: tests/lead-reports/drill-verification.spec.ts | I115: Pass
A116: LR-DDV-05 | B116: Drill-down verification: Source & Channel grouped by Broker ("Leads" of every row) | C116: Lead Reports workbook (Drill-down Verification) | D116: Lead Reports | E116: REQ-LR-09 | G116: Yes | H116: tests/lead-reports/drill-verification.spec.ts | I116: Pass
A117: LR-DDV-06 | B117: Drill-down verification: Source & Channel grouped by Salesperson ("Leads" of every row) | C117: Lead Reports workbook (Drill-down Verification) | D117: Lead Reports | E117: REQ-LR-09 | G117: Yes | H117: tests/lead-reports/drill-verification.spec.ts | I117: Pass
A118: LR-DDV-07 | B118: Drill-down verification: Source & Channel grouped by Project ("Leads" of every row) | C118: Lead Reports workbook (Drill-down Verification) | D118: Lead Reports | E118: REQ-LR-09 | G118: Yes | H118: tests/lead-reports/drill-verification.spec.ts | I118: Pass
A119: LR-DDV-08 | B119: Drill-down verification: Source & Channel grouped by Nationality ("Leads" of every row) | C119: Lead Reports workbook (Drill-down Verification) | D119: Lead Reports | E119: REQ-LR-09 | G119: Yes | H119: tests/lead-reports/drill-verification.spec.ts | I119: Pass
A120: LR-DDV-09 | B120: Drill-down verification: Source & Channel grouped by Prospect Type ("Leads" of every row) | C120: Lead Reports workbook (Drill-down Verification) | D120: Lead Reports | E120: REQ-LR-09 | G120: Yes | H120: tests/lead-reports/drill-verification.spec.ts | I120: Pass
A121: LR-DDV-10 | B121: Drill-down verification: Aging & Follow-up (cards and Open Leads by Salesperson) | C121: Lead Reports workbook (Drill-down Verification) | D121: Lead Reports | E121: REQ-LR-09 | G121: Yes | H121: tests/lead-reports/drill-verification.spec.ts | I121: Pass
A122: LR-DDV-11 | B122: Drill-down verification: Qualification & Conversion — View lost leads = Lost Reasons total | C122: Lead Reports workbook (Drill-down Verification) | D122: Lead Reports | E122: REQ-LR-09 | G122: Yes | H122: tests/lead-reports/drill-verification.spec.ts | I122: Pass
A123: LR-DDV-12 | B123: Drill-down verification: Salesperson Scorecard (every salesperson × every count column) | C123: Lead Reports workbook (Drill-down Verification) | D123: Lead Reports | E123: REQ-LR-09 | G123: Yes | H123: tests/lead-reports/drill-verification.spec.ts | I123: Pass
A124: LR-DDV-13 | B124: Drill-down verification: A list with a header filter applied (Lead Source) | C124: Lead Reports workbook (Drill-down Verification) | D124: Lead Reports | E124: REQ-LR-09 | G124: Yes | H124: tests/lead-reports/drill-verification.spec.ts | I124: Pass
A125: LR-147 | B125: Verify All filters together return only records matching every selected filter | C125: Lead Reports workbook | D125: Lead Reports | E125: REQ-LR-04 | F125: High | G125: Yes | H125: tests/lead-reports/filter-combinations.spec.ts | I125: Pass
A126: LR-148 | B126: Verify changing one filter recalculates all KPI cards and report tables | C126: Lead Reports workbook | D126: Lead Reports | E126: REQ-LR-04 | F126: High | G126: Yes | H126: tests/lead-reports/filter-combinations.spec.ts | I126: Pass
A127: LR-149 | B127: Verify clearing one selected filter restores only that filter's data while retaining other filters | C127: Lead Reports workbook | D127: Lead Reports | E127: REQ-LR-04 | F127: High | G127: Yes | H127: tests/lead-reports/filter-combinations.spec.ts | I127: Pass
...

Sheet Defects
A1: Defect ID | B1: Defect | C1: Severity | D1: Linked test cases | E1: Linked requirements | F1: Failing tests in this run | G1: Status in this run
A2: DEF-01 | B2: Report modules open on "Last 12 months" instead of "This month" (product decision pending) | C2: Medium | D2: SAL-05, INV-05, CUS-05, BRK-05, MKT-05, RES-05, SPA-05, COL-05, EXC-05, LDR-05, RA-013, LR-017, LR-OBS-01 | E2: REQ-BRK-03, REQ-COL-03, REQ-CUS-03, REQ-EXC-03, REQ-INV-03, REQ-LR-02, REQ-LR-16, REQ-MKT-03, REQ-RES-03, REQ-SAL-03, REQ-SC-02, REQ-SPA-03 | F2: =COUNTIFS('Test Case Mapping'!$J$2:$J$600,"*"&A2&"*",'Test Case Mapping'!$I$2:$I$600,"Fail") | G2: =IF(F2>0,"Open (reproduced)","Not reproduced")
A3: DEF-02 | B3: Open Opportunities: hub / dashboard value differs from Sales Reports | C3: High | D3: X-02, RA-002, RA-059 | E3: REQ-SC-01, REQ-SC-06, REQ-X-01 | F3: =COUNTIFS('Test Case Mapping'!$J$2:$J$600,"*"&A3&"*",'Test Case Mapping'!$I$2:$I$600,"Fail") | G3: =IF(F3>0,"Open (reproduced)","Not reproduced")
A4: DEF-03 | B4: Pipeline and Weighted pipeline: hub value differs from Sales Reports | C4: High | D4: X-03, X-04, RA-006, RA-007 | E4: REQ-SC-01, REQ-X-01 | F4: =COUNTIFS('Test Case Mapping'!$J$2:$J$600,"*"&A4&"*",'Test Case Mapping'!$I$2:$I$600,"Fail") | G4: =IF(F4>0,"Open (reproduced)","Not reproduced")
A5: DEF-04 | B5: Units Reserved / Units Sold: hub value differs from Inventory Reports | C5: High | D5: X-06, X-07, RA-004, RA-005 | E5: REQ-SC-01, REQ-X-01 | F5: =COUNTIFS('Test Case Mapping'!$J$2:$J$600,"*"&A5&"*",'Test Case Mapping'!$I$2:$I$600,"Fail") | G5: =IF(F5>0,"Open (reproduced)","Not reproduced")
A6: DEF-05 | B6: Won opportunities this month: dashboard differs from Sales Reports | C6: High | D6: X-10 | E6: REQ-X-01 | F6: =COUNTIFS('Test Case Mapping'!$J$2:$J$600,"*"&A6&"*",'Test Case Mapping'!$I$2:$I$600,"Fail") | G6: =IF(F6>0,"Open (reproduced)","Not reproduced")
A7: DEF-06 | B7: Active Leads: Leads page formula differs from hub / Lead Reports Open Leads Now | C7: High | D7: L-10, RA-064 | E7: REQ-SC-07, REQ-X-01 | F7: =COUNTIFS('Test Case Mapping'!$J$2:$J$600,"*"&A7&"*",'Test Case Mapping'!$I$2:$I$600,"Fail") | G7: =IF(F7>0,"Open (reproduced)","Not reproduced")
A8: DEF-07 | B8: Collection rate above 100% (does not equal Received ÷ Scheduled) | C8: High | D8: COL-14, M-03, RA-058 | E8: REQ-COL-06, REQ-SC-06 | F8: =COUNTIFS('Test Case Mapping'!$J$2:$J$600,"*"&A8&"*",'Test Case Mapping'!$I$2:$I$600,"Fail") | G8: =IF(F8>0,"Open (reproduced)","Not reproduced")
A9: DEF-08 | B9: Customer Reports SPA value differs from SPA Reports signed value | C9: High | D9: CUS-14, RA-018 | E9: REQ-CUS-06, REQ-SC-02 | F9: =COUNTIFS('Test Case Mapping'!$J$2:$J$600,"*"&A9&"*",'Test Case Mapping'!$I$2:$I$600,"Fail") | G9: =IF(F9>0,"Open (reproduced)","Not reproduced")
A10: DEF-09 | B10: Inventory "Available" card differs from the Availability Summary total | C10: Medium | D10: INV-15 | E10: REQ-INV-06 | F10: =COUNTIFS('Test Case Mapping'!$J$2:$J$600,"*"&A10&"*",'Test Case Mapping'!$I$2:$I$600,"Fail") | G10: =IF(F10>0,"Open (reproduced)","Not reproduced")
A11: DEF-10 | B11: Sales Reports crashes / shows nothing on incomplete or empty API data | C11: Medium | D11: RA-095, RA-097 | E11: REQ-SC-12 | F11: =COUNTIFS('Test Case Mapping'!$J$2:$J$600,"*"&A11&"*",'Test Case Mapping'!$I$2:$I$600,"Fail") | G11: =IF(F11>0,"Open (reproduced)","Not reproduced")
A12: DEF-11 | B12: Accessibility: unlabelled controls, low contrast, screen-reader and alert issues | C12: Medium | D12: RA-120, RA-122, RA-123, RA-124 | E12: REQ-SC-16 | F12: =COUNTIFS('Test Case Mapping'!$J$2:$J$600,"*"&A12&"*",'Test Case Mapping'!$I$2:$I$600,"Fail") | G12: =IF(F12>0,"Open (reproduced)","Not reproduced")
A13: DEF-12 | B13: Lead Reports: browser Back loses the tab; Esc does not close the drill-down list | C13: Low | D13: LR-014, LR-074, LR-OBS-03 | E13: REQ-LR-01, REQ-LR-09, REQ-LR-16 | F13: =COUNTIFS('Test Case Mapping'!$J$2:$J$600,"*"&A13&"*",'Test Case Mapping'!$I$2:$I$600,"Fail") | G13: =IF(F13>0,"Open (reproduced)","Not reproduced")
... A18: DEF-17 | B18: Project filter: 9 project codes with leads cannot be selected; duplicate salesperson option | C18: Medium | D18: LR-156, LR-165 | E18: REQ-LR-04, REQ-LR-05 | F18: =COUNTIFS('Test Case Mapping'!$J$2:$J$600,"*"&A18&"*",'Test Case Mapping'!$I$2:$I$600,"Fail") | G18: =IF(F18>0,"Open (reproduced)","Not reproduced")
A20: Failing tests not linked to a known defect (to triage):
A21: None

Sheet How to read
A1: Traceability Matrix | B1: One row per requirement: which test cases cover it, how many are automated, the latest result and the defects linked to it. Counts are formulas over the Test Case Mapping sheet.
A2: Test Case Mapping | B2: One row per test case (every automated test, including workbook test cases that stay manual and are registered as Skipped). Filter by Requirement ID, Page or Latest Result.
A3: Defects | B3: Known defects with the test cases that detect them; "Status in this run" shows whether any of those tests failed. Failing tests without a known defect are listed under "to triage".
A4: Coverage | B4: Automated = every test case of the requirement runs automatically; Partly manual = some are registered as manual (need other roles, data changes or a load tool); Manual only = none automated.
A5: Execution status | B5: Pass = all executed tests passed; Fail = only failures; Partly failing = some pass, some fail; Skipped = data or setup not available (e.g. database checks are switched off with SKIP_DB_TESTS=true).
A6: Requirements | B6: There is no separate requirement document, so requirements are the features of each report page, taken from the test-case workbooks and the pages themselves. Business scenarios keep their Test Area from Reports_Analytics_Test_Scenarios.xlsx.
A7: Updating | B7: Change a "Latest Result" on Test Case Mapping and the matrix and summary recalculate. Regenerating after a new run is done from the automation suite.
